Workbook

Sheet Cover Page
D5: [Insert logo]
C10: Privacy Impact Assessment Report In compliance with the Data Privacy Act of 2012
C25: Document Code:
C26: Effective Date:
C27: Review Date:
C28: Version Control No.:

Sheet Project-System Description 
B2: Project-System Description
B3: Description
B4: The system is a | D4: designed to manage | F4: of personal data within
B6: Key Processes include:
B7: Data Collection | C7: Gathering data through
B8: Data Usage | C8: Using data for
B9: Data Storage | C9: Secure storage in
B10: Data Disposal | C10: Secure disposal in line with
B12: If applicable:
B13: The system integrates with existing programs such as
B14: Supported by documents like the Requirements and Design Specifications
B16: Purpose
B17: The system aims to
B19: Scope of the PIA
B20: This Privacy Impact Assessment (PIA) reviews privacy risks in the | G20: related to the | H20: =E4 -> 0 | I20: of personal data.
B21: It examines the data types, legal basis, security,
B22: This PIA does not cover non-data protection issues or activities that do not involve personal data.

Sheet P1 Threshold Analysis
B2: Threshold Analysis
B3: No. | C3: Question | D3: Yes/No | E3: Response
B4: 1 | C4: Does the project or system collect, use, keep, share, or dispose of personal information?
B5: 2 | C5: Does the project or system collect, use, keep, share, or dispose of sensitive personal information or privileged information?
B6: 3 | C6: Is processing regular and not just a one-time thing?
B7: 4 | C7: Does the project or system include information about vulnerable individuals?
B8: 5 | C8: Does the processing involve records of 250 or more individuals?
B9: 6 | C9: Does the processing use off-the-shelf software?
B10: 7 | C10: Are you using individuals’ information for a purpose other than originally intended?
B11: 8 | C11: Will individuals’ information be used for marketing, online services, systematic monitoring, tracking or observing their location or behavior?
B12: 9 | C12: Will individuals’ information be shared with organizations or people who have not previously had regular access to it?
B13: 10 | C13: Does the project or system use new technology that may be seen as privacy-intrusive?
B14: 11 | C14: Will the processing use automated decision making, AI or profiling with legal or similar significant effect?
B15: 12 | C15: Will the processing prevent individuals from exercising a right or using a service or a contract?
C17: IS PIA REQUIRED? | D17: =IF(OR(AND(D4="Yes", COUNTIF(D5:D15, "Yes")>0), AND(D4="No", D5="Yes", COUNTIF(D5:D15, "Yes")>0)), "Yes", "No") -> No | E17: =IF(D17="Yes", "PIA Required - Proceed to the next section", IF(D17="No", "PIA Not Required - Proceed to Sign-Off","")) -> PIA Not Required - Proceed to Sign-Off

Sheet P1 Stakeholder Engagement
B2: Stakeholder(s) Engagement
B3: Name/Position | C3: Role | D3: Involvement | E3: Inputs/ Recommendations

Sheet P2 Data Mapping
B2: Data Processing System Details
B4: Is DPS Manual, Electronic, or Both?
B5: Data Processing System Name
B6: Basis for Processing Personal Information | D6: Basis for Processing Sensitive Personal Information (If applicable)
B8: Purpose of Processing | D8: Intended Future Purpose (if any)
B10: Description of the category or categories of data subject
B12: Type of Personal Data | C12: Categories of Personal Data | D12: Amount of personal data (estimate) | F12: PIP/PIC
B13: Personal Information
B15: Sensitive Personal Information
B17: Privileged Information
B18: Is processing done as PIC or PIP?
B19: Is the system outsourced or subcontracted?
B20: Name of PIP | D20: Email Address | F20: Contact No.
B22: Name of PIC
B24: Name of DPO | D24: Email Address | F24: Contact No.
B26: Is the system a publicly facing online mobile or web-based application?
B27: Is the system External and/or Internal facing?
B28: Is there any notification regarding any automated decision-making operation and/or profiling?
B29: Lawful basis of processing personal data | E29: =IF($D$28="No", "N/A", IF($D$28="Automated decision-making", "Insert details below", IF($D$28="Profiling", "Insert details below", IF($D$28="Both", "Insert details below",""))))
B31: Other relevant information pertaining to the specified lawful basis | E31: =IF($D$28="No", "N/A", IF($D$28="Automated decision-making", "Insert details below", IF($D$28="Profiling", "Insert details below", IF($D$28="Both", "Insert details below",""))))
B33: Is consent used as the basis for processing?
B34: Consent form or any other proof of obtaining consent? (Specify below)
B36: Retention period for the data processed | E36: =IF($D$28="No", "N/A", IF($D$28="Automated decision-making", "Insert details below", IF($D$28="Profiling", "Insert details below", IF($D$28="Both", "Insert details below",""))))
B38: Methods and logic utilized for automated processing | E38: =IF($D$28="No", "N/A", IF($D$28="Automated decision-making", "Insert details below", IF($D$28="Profiling", "Insert details below", IF($D$28="Both", "Insert details below",""))))
B40: Possible decisions relating to the data subject based on the processed data, particularly if they would significantly affect his or her rights and freedoms | E40: =IF($D$28="No", "N/A", IF($D$28="Automated decision-making", "Insert details below", IF($D$28="Profiling", "Insert details below", IF($D$28="Both", "Insert details below",""))))
B42: Description of Security Measures
B43: Organizational
B45: Physical
B47: Technical
B51: General Information of the Data Life Cycle
B53: Collection
B54: When is the personal data collected? | F54: Who collects the personal data? | H54: From whom is the personal data collected?
B58: Use
B59: Position & Department | D59: Scope/Module | G59: File Name | I59: Purpose
B70: Disclosure
B71: Category of recipients to whom the data might be disclosed | C71: Recipients | D71: Data Sharing Purpose | F71: Is there any Data Sharing Agreements with other parties? | H71: Name of PIC | I71: Is the personal data transferred outside of the Philippines?
B72: Internal | D72: N/A | F72: N/A | H72: N/A | I72: N/A
D73: N/A | F73: N/A | H73: N/A | I73: N/A
B74: External
B76: Retention and Disposal
B77: List of all information repositories holding personal data | C77: Type of Media | D77: Location of the repositories | F77: City, Country | G77: Retention Period with Reckoning date/time | H77: Basis for Retention | I77: Disposal/Destruction/Deletion Procedure

Sheet P3 Gen Data Privacy Principles
B2: Note: The default risk rating is based on inherent risk, calculated using data subject impact and likelihood. This rating is not final and may change based on your assessment as the process or system owner. To request a change, consult your Data Protection Officer (DPO). If approved, the rating can be updated.
B5: Transparency
B6: No. | C6: Questions | F6: Yes/No/ N/A | G6: Response | H6: Threats/Vulnerabilities | I6: Risk | J6: Legal Basis | K6: Impact | L6: Probability | M6: Risk Rating
B7: 1 | C7: 1. Are data subjects informed of the following details before or shortly after their personal data is collected (Privacy Notice)? Check all present | H7: =IF(F7="No", "Absence of a comprehensive and timely privacy notice creates a transparency gap, weakening data subjects' ability to make informed decisions and exercise their rights.", "") | I7: =IF(F7="No", "Violation of general privacy principles – Transparency Violation of data subject rights - Rights to be informed", "") | J7: =IF(F7="No", "SEC. 11, DPA SEC. 16(a)(b), DPA", "") | K7: =IF(AND(F7="No", 'P1 Threshold Analysis'!D5="Yes"), 4, IF(AND(F7="No", COUNTIF(F8:F17, "False")>9), 4, IF(AND(F7="No", COUNTIF(F8:F17, "True")>0), 3, ""))) | L7: =IF(AND(F7="No", 'P1 Threshold Analysis'!D5="Yes"), 4, IF(AND(F7="No", COUNTIF(F8:F17, "False")>9), 4, IF(AND(F7="No", COUNTIF(F8:F17, "True")>0), 3, ""))) | M7: =IF(OR(K7="", L7=""), "", IF(K7*L7>=10, IF(K7*L7<=16, "High Risk", ""), IF(K7*L7>=6, IF(K7*L7<=9, "Medium Risk", ""), IF(K7*L7>=2, IF(K7*L7<=4, "Low Risk", ""), IF(K7*L7=1, "Negligible", "")))))
C8: a. Description of the personal data to be processed | F8: FALSE
C9: b. Purposes of processing, including direct marketing, profiling or historical, statistical or scientific purpose if applicable | F9: FALSE
C10: c. Basis of processing, when not based on consent | F10: FALSE
C11: d. Scope and method of processing | F11: FALSE
C12: e. Recipients or categories of recipients who may receive the personal data | F12: FALSE
C13: f. Methods used for automated access (cookie notification), if allowed by the data subject, including the extent of the authorization, the logic involved, and the significance and potential consequences of such processing | F13: FALSE | AZ13: Use of complex or technical language in privacy notices makes it difficult for data subjects to understand how their personal data is processed, increasing the risk of uninformed consent (if processing is based on consent) and non-compliance with transparency obligations.
C14: g. Risks and safeguards involved in the processing | F14: FALSE
C15: h. Identity and contact details of the PIC (your organization) or its representative (DPO) | F15: FALSE
C16: i. Retention period | F16: FALSE
C17: j. Data subject rights and the process for exercising them | F17: FALSE
B18: 2 | C18: Is information and communication about personal data processing easy to access and understand, using clear and plain language (Privacy Notice)? | H18: =IF(F18="No", "Use of complex or technical language in privacy notices makes it difficult for data subjects to understand how their personal data is processed, increasing the risk of uninformed consent and non-compliance with transparency obligations.", "N/A") -> N/A | I18: =IF(F18="No","Violation of general privacy principles – Transparency", "") | J18: =IF(F18="No","SEC. 11, DPA ", "") | K18: =IF(AND(F7="No", COUNTIF(F8:F17, "False")>9), 4, IF(AND(F18="No", 'P1 Threshold Analysis'!D5="Yes"), 3, IF(AND(F18="No", COUNTIF(F8:F17, "FALSE")>0, 'P1 Threshold Analysis'!D4="Yes", 'P1 Threshold Analysis'!D5="No"), 2, ""))) | L18: =IF(AND(F7="No", COUNTIF(F8:F17, "False")>9), 4, IF(AND(F18="No", 'P1 Threshold Analysis'!D5="Yes"), 3, IF(AND(F18="No", COUNTIF(F8:F17, "FALSE")>0, 'P1 Threshold Analysis'!D4="Yes", 'P1 Threshold Analysis'!D5="No"), 2, ""))) | M18: =IF(OR(K18="", L18=""), "", IF(K18*L18>=10, IF(K18*L18<=16, "High Risk", ""), IF(K18*L18>=6, IF(K18*L18<=9, "Medium Risk", ""), IF(K18*L18>=2, IF(K18*L18<=4, "Low Risk", ""), IF(K18*L18=1, "Negligible", "")))))
B19: Legitimate Purpose / Lawfulness
B20: 1 | C20: Is the processing of personal data compatible with a declared and specified purpose which are not contrary to law, morals, or public policy? | H20: =IF(F20="No", "Processing personal data for purposes that are incompatible with the declared purpose and contrary to law, morals, or public policy may lead to regulatory sanctions, reputational damage, and loss of public trust.", "") | I20: =IF(F20="No", "Violation of general privacy principles – Legitimate Purpose", "") | J20: =IF(F20="No", " SEC. 11, DPA", "") | K20: =IF(AND(F20="No", 'P1 Threshold Analysis'!D5="Yes"),4, IF(AND(F20="No", 'P1 Threshold Analysis'!D4="Yes"), 3,"")) | L20: =IF(AND(F20="No", 'P1 Threshold Analysis'!D5="Yes"),4, IF(AND(F20="No", 'P1 Threshold Analysis'!D4="Yes"), 3,"")) | M20: =IF(OR(K20="", L20=""), "", IF(K20*L20>=10, IF(K20*L20<=16, "High Risk", ""), IF(K20*L20>=6, IF(K20*L20<=9, "Medium Risk", ""), IF(K20*L20>=2, IF(K20*L20<=4, "Low Risk", ""), IF(K20*L20=1, "Negligible", "")))))
B21: 2 | C21: Is the processing based on Section 4 (for special cases), Section 12 (for personal information), or Section 13 (for sensitive and privileged information) of the DPA? | H21: =IF(F21="No", "Processing personal data without a valid legal basis under Sections 4, 12, or 13 of the Data Privacy Act exposes the organization to legal liabilities, and penalties.", "") | I21: =IF(F21="No", "Violation of general privacy principles – Legitimate Purpose", "") | J21: =IF(F21="No", " SEC. 11, DPA", "") | K21: =IF(AND(F21="No", 'P1 Threshold Analysis'!D5="Yes"),4, IF(AND(F21="No", 'P1 Threshold Analysis'!D4="Yes"), 3,"")) | L21: =IF(AND(F21="No", 'P1 Threshold Analysis'!D5="Yes"),4, IF(AND(F21="No", 'P1 Threshold Analysis'!D4="Yes"), 3,"")) | M21: =IF(OR(K21="", L21=""), "", IF(K21*L21>=10, IF(K21*L21<=16, "High Risk", ""), IF(K21*L21>=6, IF(K21*L21<=9, "Medium Risk", ""), IF(K21*L21>=2, IF(K21*L21<=4, "Low Risk", ""), IF(K21*L21=1, "Negligible", "")))))
B22: Proportionality / Data minimization
B23: Personal Data/Functions | D23: Adequate (enough to fulfil the purpose) | E23: Relevant & Suitable (related & appropriate) | F23: Necessary | G23: Remarks | H23: Threats/Vulnerabilities | I23: Risk | J23: Legal Basis | K23: Impact | L23: Probability | M23: Risk Rating
B24: Name, Age | D24: No | E24: No | F24: Required | H24: =IF(OR(D24="No", E24="No", F24="No", F24="Optional"), "For Collection Form" & CHAR(10) & "Collecting excessive or irrelevant data increases the risk of misuse, breaches, and non-compliance with data minimization." & CHAR(10) & CHAR(10) & "For Off-the-Shelf Software" & CHAR(10) & "Pre-enabled features may process data without a lawful basis, risking unauthorized use.", "") -> For Collection Form Collecting excessive or irrelevant data increases the risk of misuse, breaches, and non-compliance with data minimization. For Off-the-Shelf Software Pre-enabled features may process data without a lawful basis, risking unauthorized use. | I24: =IF(OR(D24="No", E24="No", F24="No", F24="Optional"), "Violation of general privacy principles – Proportionality / Data Minimization" & CHAR(10) & CHAR(10) & "For Off-the-Shelf Software" & CHAR(10) & "Violation of general privacy principles – Proportionality / Data Minimization / Privacy-by-Design / Privacy-by-Default", "") -> Violation of general privacy principles – Proportionality / Data Minimization For Off-the-Shelf Software Violation of general privacy principles – Proportionality / Data Minimization / Privacy-by-Design / Privacy-by-Default | J24: =IF(OR(D24="No", E24="No", F24="Optional"), "SEC. 11, DPA ", "") -> SEC. 11, DPA | K24: =IF(AND('P1 Threshold Analysis'!D5="Yes", OR(D24="No", E24="No", F24="No", F24="Optional")), 4, IF(AND('P1 Threshold Analysis'!D4="Yes", OR(D24="No", E24="No", F24="No", F24="Optional")), 3, "")) | L24: =IF(AND('P1 Threshold Analysis'!D5="Yes", OR(D24="No", E24="No", F24="No", F24="Optional")), 4, IF(AND('P1 Threshold Analysis'!D4="Yes", OR(D24="No", E24="No", F24="No", F24="Optional")), 3, "")) | M24: =IF(OR(K24="", L24=""), "", IF(K24*L24>=10, IF(K24*L24<=16, "High Risk", ""), IF(K24*L24>=6, IF(K24*L24<=9, "Medium Risk", ""), IF(K24*L24>=2, IF(K24*L24<=4, "Low Risk", ""), IF(K24*L24=1, "Negligible", "")))))
H25: =IF(OR(D25="No", E25="No", F25="No", F25="Optional"), "For Collection Form" & CHAR(10) & "Collecting excessive or irrelevant data increases the risk of misuse, breaches, and non-compliance with data minimization." & CHAR(10) & CHAR(10) & "For Off-the-Shelf Software" & CHAR(10) & "Pre-enabled features may process data without a lawful basis, risking unauthorized use.", "") | I25: =IF(OR(D25="No", E25="No", F25="No", F25="Optional"), "Violation of general privacy principles – Proportionality / Data Minimization" & CHAR(10) & CHAR(10) & "For Off-the-Shelf Software" & CHAR(10) & "Violation of general privacy principles – Proportionality / Data Minimization / Privacy-by-Design / Privacy-by-Default", "") | J25: =IF(OR(D25="No", E25="No", F25="No", F25="Optional"), "SEC. 11, DPA ", "") | K25: =IF(AND('P1 Threshold Analysis'!D5="Yes", OR(D25="No", E25="No", F25="No", F25="Optional")), 4, IF(AND('P1 Threshold Analysis'!D4="Yes", OR(D25="No", E25="No", F25="No", F25="Optional")), 3, "")) | L25: =IF(AND('P1 Threshold Analysis'!D5="Yes", OR(D25="No", E25="No", F25="No", F25="Optional")), 4, IF(AND('P1 Threshold Analysis'!D4="Yes", OR(D25="No", E25="No", F25="No", F25="Optional")), 3, "")) | M25: =IF(OR(K25="", L25=""), "", IF(K25*L25>=10, IF(K25*L25<=16, "High Risk", ""), IF(K25*L25>=6, IF(K25*L25<=9, "Medium Risk", ""), IF(K25*L25>=2, IF(K25*L25<=4, "Low Risk", ""), IF(K25*L25=1, "Negligible", "")))))
H26: =IF(OR(D26="No", E26="No", F26="No", F26="Optional"), "For Collection Form" & CHAR(10) & "Collecting excessive or irrelevant data increases the risk of misuse, breaches, and non-compliance with data minimization." & CHAR(10) & CHAR(10) & "For Off-the-Shelf Software" & CHAR(10) & "Pre-enabled features may process data without a lawful basis, risking unauthorized use.", "") | I26: =IF(OR(D26="No", E26="No", F26="No", F26="Optional"), "Violation of general privacy principles – Proportionality / Data Minimization" & CHAR(10) & CHAR(10) & "For Off-the-Shelf Software" & CHAR(10) & "Violation of general privacy principles – Proportionality / Data Minimization / Privacy-by-Design / Privacy-by-Default", "") | J26: =IF(OR(D26="No", E26="No", F26="No", F26="Optional"), "SEC. 11, DPA ", "") | K26: =IF(AND('P1 Threshold Analysis'!D5="Yes", OR(D26="No", E26="No", F26="No", F26="Optional")), 4, IF(AND('P1 Threshold Analysis'!D4="Yes", OR(D26="No", E26="No", F26="No", F26="Optional")), 3, "")) | L26: =IF(AND('P1 Threshold Analysis'!D5="Yes", OR(D26="No", E26="No", F26="No", F26="Optional")), 4, IF(AND('P1 Threshold Analysis'!D4="Yes", OR(D26="No", E26="No", F26="No", F26="Optional")), 3, "")) | M26: =IF(OR(K26="", L26=""), "", IF(K26*L26>=10, IF(K26*L26<=16, "High Risk", ""), IF(K26*L26>=6, IF(K26*L26<=9, "Medium Risk", ""), IF(K26*L26>=2, IF(K26*L26<=4, "Low Risk", ""), IF(K26*L26=1, "Negligible", "")))))
H27: =IF(OR(D27="No", E27="No", F27="No", F27="Optional"), "For Collection Form" & CHAR(10) & "Collecting excessive or irrelevant data increases the risk of misuse, breaches, and non-compliance with data minimization." & CHAR(10) & CHAR(10) & "For Off-the-Shelf Software" & CHAR(10) & "Pre-enabled features may process data without a lawful basis, risking unauthorized use.", "") | I27: =IF(OR(D27="No", E27="No", F27="No", F27="Optional"), "Violation of general privacy principles – Proportionality / Data Minimization" & CHAR(10) & CHAR(10) & "For Off-the-Shelf Software" & CHAR(10) & "Violation of general privacy principles – Proportionality / Data Minimization / Privacy-by-Design / Privacy-by-Default", "") | J27: =IF(OR(D27="No", E27="No", F27="No", F27="Optional"), "SEC. 11, DPA ", "") | K27: =IF(AND('P1 Threshold Analysis'!D5="Yes", OR(D27="No", E27="No", F27="No", F27="Optional")), 4, IF(AND('P1 Threshold Analysis'!D4="Yes", OR(D27="No", E27="No", F27="No", F27="Optional")), 3, "")) | L27: =IF(AND('P1 Threshold Analysis'!D5="Yes", OR(D27="No", E27="No", F27="No", F27="Optional")), 4, IF(AND('P1 Threshold Analysis'!D4="Yes", OR(D27="No", E27="No", F27="No", F27="Optional")), 3, "")) | M27: =IF(OR(K27="", L27=""), "", IF(K27*L27>=10, IF(K27*L27<=16, "High Risk", ""), IF(K27*L27>=6, IF(K27*L27<=9, "Medium Risk", ""), IF(K27*L27>=2, IF(K27*L27<=4, "Low Risk", ""), IF(K27*L27=1, "Negligible", "")))))
H28: =IF(OR(D28="No", E28="No", F28="No", F28="Optional"), "For Collection Form" & CHAR(10) & "Collecting excessive or irrelevant data increases the risk of misuse, breaches, and non-compliance with data minimization." & CHAR(10) & CHAR(10) & "For Off-the-Shelf Software" & CHAR(10) & "Pre-enabled features may process data without a lawful basis, risking unauthorized use.", "") | I28: =IF(OR(D28="No", E28="No", F28="No", F28="Optional"), "Violation of general privacy principles – Proportionality / Data Minimization" & CHAR(10) & CHAR(10) & "For Off-the-Shelf Software" & CHAR(10) & "Violation of general privacy principles – Proportionality / Data Minimization / Privacy-by-Design / Privacy-by-Default", "") | J28: =IF(OR(D28="No", E28="No", F28="No", F28="Optional"), "SEC. 11, DPA ", "") | K28: =IF(AND('P1 Threshold Analysis'!D5="Yes", OR(D28="No", E28="No", F28="No", F28="Optional")), 4, IF(AND('P1 Threshold Analysis'!D4="Yes", OR(D28="No", E28="No", F28="No", F28="Optional")), 3, "")) | L28: =IF(AND('P1 Threshold Analysis'!D5="Yes", OR(D28="No", E28="No", F28="No", F28="Optional")), 4, IF(AND('P1 Threshold Analysis'!D4="Yes", OR(D28="No", E28="No", F28="No", F28="Optional")), 3, "")) | M28: =IF(OR(K28="", L28=""), "", IF(K28*L28>=10, IF(K28*L28<=16, "High Risk", ""), IF(K28*L28>=6, IF(K28*L28<=9, "Medium Risk", ""), IF(K28*L28>=2, IF(K28*L28<=4, "Low Risk", ""), IF(K28*L28=1, "Negligible", "")))))
B29: Fairness
B30: 1 | C30: Is the Privacy Notice / Consent Form presented objectively and neutrally, without deceptive or manipulative language or design? | H30: =IF(F30="No", "The use of biased or manipulative language in the Privacy Notice/Consent Form undermines the clarity of consent, potentially leading to invalid consent and non-compliance with data protection regulations. ", "") | I30: =IF(F30="No", "Violation of general privacy principles – Fairness ", "") | J30: =IF(F30="No", "SEC. 11, DPA ", "") | K30: =IF(AND(F30="No", 'P1 Threshold Analysis'!D5="Yes"), 4, IF(AND(F30="No", 'P1 Threshold Analysis'!D4="Yes"),3,"")) | L30: =IF(AND(F30="No", 'P1 Threshold Analysis'!D5="Yes"), 4, IF(AND(F30="No", 'P1 Threshold Analysis'!D4="Yes"),3,"")) | M30: =IF(OR(K30="", L30=""), "", IF(K30*L30>=10, IF(K30*L30<=16, "High Risk", ""), IF(K30*L30>=6, IF(K30*L30<=9, "Medium Risk", ""), IF(K30*L30>=2, IF(K30*L30<=4, "Low Risk", ""), IF(K30*L30=1, "Negligible", "")))))
B31: Data Quality / Accuracy
B32: 1 | C32: Is personal data accurate, and kept up to date? Check all present | H32: =IF(F32="No", "Inaccurate or outdated personal data can lead to incorrect decisions, harm to data subjects, and non-compliance with data accuracy requirements, undermining the integrity of the processing system. ", "") | I32: =IF(F32="No", "Violation of general privacy principles – Accuracy ", "") | J32: =IF(F32="No", "SEC. 11, DPA ", "") | K32: =IF(AND(F32="No", 'P1 Threshold Analysis'!D5="Yes"), 4, IF(AND(F32="No", 'P1 Threshold Analysis'!D4="Yes"),3,"")) | L32: =IF(AND(F32="No", 'P1 Threshold Analysis'!D5="Yes"), 4, IF(AND(F32="No", 'P1 Threshold Analysis'!D4="Yes"),3,"")) | M32: =IF(OR(K32="", L32=""), "", IF(K32*L32>=10, IF(K32*L32<=16, "High Risk", ""), IF(K32*L32>=6, IF(K32*L32<=9, "Medium Risk", ""), IF(K32*L32>=2, IF(K32*L32<=4, "Low Risk", ""), IF(K32*L32=1, "Negligible", "")))))
C33: a. Verify data at collection | F33: FALSE
C34: b. Review and update personal data regularly | F34: FALSE
C35: c. Allow users to update their personal data securely | F35: FALSE
C36: d. Use reliable sources when updating records | F36: FALSE
B37: 2 | C37: Is inaccurate or incomplete data rectified, supplemented, destroyed or their further processing restricted? Check all present | H37: =IF(F37="No", "Failure to rectify or restrict processing of inaccurate or incomplete data compromises data quality and may result in violations of data subjects’ rights. ", "") | I37: =IF(F37="No", "Violation of general privacy principles – Accuracy ", "") | J37: =IF(F37="No", "SEC. 11, DPA ", "") | K37: =IF(AND(F37="No", 'P1 Threshold Analysis'!D5="Yes"), 4, IF(AND(F37="No", 'P1 Threshold Analysis'!D4="Yes"),3,"")) | L37: =IF(AND(F37="No", 'P1 Threshold Analysis'!D5="Yes"), 4, IF(AND(F37="No", 'P1 Threshold Analysis'!D4="Yes"),3,"")) | M37: =IF(OR(K37="", L37=""), "", IF(K37*L37>=10, IF(K37*L37<=16, "High Risk", ""), IF(K37*L37>=6, IF(K37*L37<=9, "Medium Risk", ""), IF(K37*L37>=2, IF(K37*L37<=4, "Low Risk", ""), IF(K37*L37=1, "Negligible", "")))))
C38: a. People can request corrections and erasure easily | F38: FALSE
C39: b. Data processing restrictions of inaccurate or incomplete data until rectified | F39: FALSE
C40: c. Secure disposal methods | F40: FALSE
B41: Purpose limitation
B42: 1 | C42: Is personal data collected for specified purpose not further processed in a manner that is incompatible with that purpose? Note: may be further processed for historical, statistical, or scientific purposes, and stored longer as allowed by law, provided appropriate security measures safeguard the data subject’s rights and freedoms. | H42: =IF(F42="No", "Processing personal data for unspecified or incompatible purposes increases the risk of unauthorized use, undermining data subject trust and exposing the organization to regulatory penalties. ", "") | I42: =IF(F42="No", "Violation of general privacy principles – Purpose Limitation Unlawful Processing - Processing of Personal Data for Unauthorized Purposes ", "") | J42: =IF(F42="No", "SEC. 11, DPA SEC. 28, DPA ", "") | K42: =IF(AND(F42="No", 'P1 Threshold Analysis'!D5="Yes"), 4, IF(AND(F42="No", 'P1 Threshold Analysis'!D4="Yes"),3,"")) | L42: =IF(AND(F42="No", 'P1 Threshold Analysis'!D5="Yes"), 4, IF(AND(F42="No", 'P1 Threshold Analysis'!D4="Yes"),3,"")) | M42: =IF(OR(K42="", L42=""), "", IF(K42*L42>=10, IF(K42*L42<=16, "High Risk", ""), IF(K42*L42>=6, IF(K42*L42<=9, "Medium Risk", ""), IF(K42*L42>=2, IF(K42*L42<=4, "Low Risk", ""), IF(K42*L42=1, "Negligible", "")))))
B43: Storage Limitation
B44: 1 | C44: Is personal data retained only for as long as necessary? Check all applicable | H44: =IF(F44="No", "Retaining personal data longer than necessary increases the risk of data breaches, unauthorized access, and non-compliance with data retention policies.", "N/A") -> N/A | I44: =IF(F44="No", "Violation of general privacy principles – Storage Limitation","") | J44: =IF(F44="No", "SEC. 11, DPA ","") | K44: =IF(AND(F44="No", 'P1 Threshold Analysis'!D5="Yes"), 4, IF(AND(F44="No", 'P1 Threshold Analysis'!D4="Yes"),3,"")) | L44: =IF(AND(F44="No", 'P1 Threshold Analysis'!D5="Yes"), 4, IF(AND(F44="No", 'P1 Threshold Analysis'!D4="Yes"),3,"")) | M44: =IF(OR(K44="", L44=""), "", IF(K44*L44>=10, IF(K44*L44<=16, "High Risk", ""), IF(K44*L44>=6, IF(K44*L44<=9, "Medium Risk", ""), IF(K44*L44>=2, IF(K44*L44<=4, "Low Risk", ""), IF(K44*L44=1, "Negligible", "")))))
C45: a. To fulfill the declared, specified, and legitimate purpose | F45: FALSE
C46: b. For the establishment, exercise or defense of legal claims; or | F46: FALSE
C47: c. For legitimate business purposes aligned with industry standards | F47: FALSE
C48: d. Retention is allowed/required by law/appropriate government agency | F48: FALSE
C49: e. Aggregated (statistics, average, total numbers) or anonymized personal data may be kept beyond the necessary period. | F49: FALSE

Sheet P3 Data Subject Rights
B2: Limitations. Data subject rights must be exercised reasonably and may be limited for public interest, protecting other rights, or when processing data for:
B3: 1 | C3: Scientific and statistical research
B4: 2 | C4: Investigation in relation to any criminal, administrative, or tax liabilities of a data subject
B5: 3 | C5: In the interest of national security, rights of data subjects nay be limited pursuant to laws, rules and regulations, or order of a competent court.
B6: 4 | C6: Limitations on the exercise of data subject rights may be applied to analogous cases where the PIC has a legitimate purpose justifying such limitation.
B8: Rights to be informed (Included under the Transparency Principle)
B9: Right to object (Applicable if the processing is based on consent or legitimate interest)
B10: No. | C10: Questions | F10: Yes/No/N/A | H10: Response | I10: Threats/Vulnerabilities | J10: Risk | K10: Legal Basis | L10: Impact | M10: Probability | N10: Risk Rating
B11: 1 | C11: (For consent) Do you obtain the data subject’s consent, evidenced by written, electronic, or recorded means, before processing their personal data? | I11: =IF(F11="No", "Failing to obtain consent in a verifiable form exposes the organization to legal risks, as consent may be challenged, leading to invalid consent and potential non-compliance with data protection laws.", "") | J11: =IF(F11="No", "Unlawful Processing - Unauthorized Processing of Personal Data","") | K11: =IF(F11="No", "SEC. 25, DPA", "") | L11: =IF(AND(F11="No", 'P1 Threshold Analysis'!D5="Yes"), 4, IF(AND(F11="No", 'P1 Threshold Analysis'!D5="No"),3,"")) | M11: =IF(AND(F11="No", 'P1 Threshold Analysis'!D5="Yes"), 4, IF(AND(F11="No", 'P1 Threshold Analysis'!D5="No"),3,"")) | N11: =IF(OR(L11="", M11=""), "", IF(L11*M11>=10, IF(L11*M11<=16, "High Risk", ""), IF(L11*M11>=6, IF(L11*M11<=9, "Medium Risk", ""), IF(L11*M11>=2, IF(L11*M11<=4, "Low Risk", ""), IF(L11*M11=1, "Negligible", "")))))
B12: 2 | C12: (For consent) Before obtaining consent, do you provide the following information clearly and concisely in the consent form or Privacy Notice? Check all present | I12: =IF(F12="No", "Inadequate or unclear information in the consent form or Privacy Notice prevents data subjects from making informed decisions, leading to invalid consent and potential non-compliance with data protection laws. ", "") | J12: =IF(F12="No", "Unlawful Processing - Unauthorized Processing of Personal Data Violation of general privacy principles – Transparency ","") | K12: =IF(F12="No", "SEC. 25, DPA SEC. 11, DPA ", "") | L12: =IF(AND(F12="No", COUNTIF(F13:G16, "False")>3), 4, IF(AND(F12="No", 'P1 Threshold Analysis'!D5="Yes", COUNTIF(F13:G16, "True")>0), 4, IF(AND(F12="No", 'P1 Threshold Analysis'!D5="No",COUNTIF(F13:G16, "True")>0), 3, ""))) | M12: =IF(AND(F12="No", COUNTIF(F13:G16, "False")>3), 4, IF(AND(F12="No", 'P1 Threshold Analysis'!D5="Yes", COUNTIF(F13:G16, "True")>0), 4, IF(AND(F12="No", 'P1 Threshold Analysis'!D5="No",COUNTIF(F13:G16, "True")>0), 3, ""))) | N12: =IF(OR(L12="", M12=""), "", IF(L12*M12>=10, IF(L12*M12<=16, "High Risk", ""), IF(L12*M12>=6, IF(L12*M12<=9, "Medium Risk", ""), IF(L12*M12>=2, IF(L12*M12<=4, "Low Risk", ""), IF(L12*M12=1, "Negligible", "")))))
C13: a. Description of the personal data to be processed | F13: FALSE
C14: b. Purpose, nature, extent, duration and scope of processing | F14: FALSE
C15: c. Identity of the PIC | F15: FALSE
C16: d. Data subject rights and the process for exercising them | F16: FALSE
B17: 3 | C17: (For consent) Does the data subject give specific consent for each declared purpose of data processing? If processing serves multiple unrelated purposes, do you provide a list and allow them to choose which ones to consent to? | I17: =IF(F17="No", "Obtaining blanket consent without allowing data subjects to choose specific purposes undermines the validity of consent and increases the risk of unlawful processing.", "") | J17: =IF(F17="No", "Unlawful Processing - Unauthorized Processing of Personal Data Violation of general privacy principles – Transparency ","") | K17: =IF(F17="No", "SEC. 25, DPA SEC. 11, DPA", "") | L17: =IF(AND(F17="No", 'P1 Threshold Analysis'!D5="Yes"), 4, IF(AND(F17="No", 'P1 Threshold Analysis'!D5="No"),3,"")) | M17: =IF(AND(F17="No", 'P1 Threshold Analysis'!D5="Yes"), 4, IF(AND(F17="No", 'P1 Threshold Analysis'!D5="No"),3,"")) | N17: =IF(OR(L17="", M17=""), "", IF(L17*M17>=10, IF(L17*M17<=16, "High Risk", ""), IF(L17*M17>=6, IF(L17*M17<=9, "Medium Risk", ""), IF(L17*M17>=2, IF(L17*M17<=4, "Low Risk", ""), IF(L17*M17=1, "Negligible", "")))))
B18: 4 | C18: Do you inform the data subject of their right to object or withdraw consent to the processing of their personal data? | I18: =IF(F18="No", "Failure to inform data subjects of their right to object or withdraw consent compromises their control over personal data and may result in non-compliance with transparency and consent requirements. ", "") | J18: =IF(F18="No", "Violation of general privacy principles – Transparency Violation of data subject rights - Rights to object ","") | K18: =IF(F18="No", "SEC. 11, DPA SEC. 34(b), IRR ", "") | L18: =IF(AND(F18="No", 'P1 Threshold Analysis'!D5="Yes"), 4, IF(AND(F18="No", 'P1 Threshold Analysis'!D5="No"),3,"")) | M18: =IF(AND(F18="No", 'P1 Threshold Analysis'!D5="Yes"), 4, IF(AND(F18="No", 'P1 Threshold Analysis'!D5="No"),3,"")) | N18: =IF(OR(L18="", M18=""), "", IF(L18*M18>=10, IF(L18*M18<=16, "High Risk", ""), IF(L18*M18>=6, IF(L18*M18<=9, "Medium Risk", ""), IF(L18*M18>=2, IF(L18*M18<=4, "Low Risk", ""), IF(L18*M18=1, "Negligible", "")))))
B19: 5 | C19: Do you inform the data subject of the scope and consequences of withdrawing consent or objecting at the start of processing and upon withdrawal/objection? | I19: =IF(F19="No", "Failing to inform data subjects about the scope and consequences of withdrawing consent or objecting to processing undermines informed decision-making and increases the risk of disputes or complaints. ", "") | J19: =IF(F19="No", "Violation of general privacy principles – Transparency Violation of data subject rights - Rights to object ","") | K19: =IF(F19="No", "SEC. 11, DPA SEC. 34(b), IRR ", "") | L19: =IF(AND(F19="No", 'P1 Threshold Analysis'!D5="Yes"), 4, IF(AND(F19="No", 'P1 Threshold Analysis'!D5="No"),3,"")) | M19: =IF(AND(F19="No", 'P1 Threshold Analysis'!D5="Yes"), 4, IF(AND(F19="No", 'P1 Threshold Analysis'!D5="No"),3,"")) | N19: =IF(OR(L19="", M19=""), "", IF(L19*M19>=10, IF(L19*M19<=16, "High Risk", ""), IF(L19*M19>=6, IF(L19*M19<=9, "Medium Risk", ""), IF(L19*M19>=2, IF(L19*M19<=4, "Low Risk", ""), IF(L19*M19=1, "Negligible", "")))))
B20: 6 | C20: When a data subject objects, do you stop processing their personal data and comply with the objection unless processing is allowed in Section 12 and 13 of the DPA, excluding consent and legitimate interest? | I20: =IF(F20="No", "Continuing to process personal data after a data subject has objected exposes the organization to legal liabilities, regulatory sanctions, and reputational damage, for failing to respect data subject rights. ", "") | J20: =IF(F20="No", "Violation of data subject rights - Rights to object ","") | K20: =IF(F20="No", "SEC. 34(b), IRR ", "") | L20: =IF(AND(F20="No", 'P1 Threshold Analysis'!D5="Yes"), 4, IF(AND(F20="No", 'P1 Threshold Analysis'!D5="No"),3,"")) | M20: =IF(AND(F20="No", 'P1 Threshold Analysis'!D5="Yes"), 4, IF(AND(F20="No", 'P1 Threshold Analysis'!D5="No"),3,"")) | N20: =IF(OR(L20="", M20=""), "", IF(L20*M20>=10, IF(L20*M20<=16, "High Risk", ""), IF(L20*M20>=6, IF(L20*M20<=9, "Medium Risk", ""), IF(L20*M20>=2, IF(L20*M20<=4, "Low Risk", ""), IF(L20*M20=1, "Negligible", "")))))
B21: 7 | C21: Do data subjects have the right to object to the processing of their personal data for direct marketing, profiling, or automated processing when it is the sole basis for decisions that significantly affect them? | I21: =IF(F21="No", "Denying data subjects the right to object to processing for direct marketing, profiling, or automated decisions increases the risk of unlawful processing and legal actions, including fines. ", "") | J21: =IF(F21="No", " Violation of data subject rights - Rights to object Unlawful Processing - Unauthorized Processing of Personal Data ","") | K21: =IF(F21="No", " SEC. 34(b), IRR SEC. 25, DPA ", "") | L21: =IF(AND(F21="No", 'P1 Threshold Analysis'!D5="Yes"), 4, IF(AND(F21="No", 'P1 Threshold Analysis'!D5="No"),3,"")) | M21: =IF(AND(F21="No", 'P1 Threshold Analysis'!D5="Yes"), 4, IF(AND(F21="No", 'P1 Threshold Analysis'!D5="No"),3,"")) | N21: =IF(OR(L21="", M21=""), "", IF(L21*M21>=10, IF(L21*M21<=16, "High Risk", ""), IF(L21*M21>=6, IF(L21*M21<=9, "Medium Risk", ""), IF(L21*M21>=2, IF(L21*M21<=4, "Low Risk", ""), IF(L21*M21=1, "Negligible", "")))))
B22: Right to access
B23: 1 | C23: Does the data subject have the right to confirm if their personal data is being processed and access details about its processing? Check all applicable | I23: =IF(F23="No", "Denying data subjects the right to confirm if their personal data is being processed and access related details undermines their rights and could result in non-compliance with data protection laws. ", "") | J23: =IF(F23="No", " Violation of data subject rights - Right to access ","") | K23: =IF(F23="No", " SEC. 16(c), DPA ", "") | L23: =IF(AND(F23="No", 'P1 Threshold Analysis'!D5="Yes"), 4, IF(AND(F23="No", 'P1 Threshold Analysis'!D4="Yes"),3,"")) | M23: =IF(AND(F23="No", 'P1 Threshold Analysis'!D5="Yes"), 4, IF(AND(F23="No", 'P1 Threshold Analysis'!D4="Yes"),3,"")) | N23: =IF(OR(L23="", M23=""), "", IF(L23*M23>=10, IF(L23*M23<=16, "High Risk", ""), IF(L23*M23>=6, IF(L23*M23<=9, "Medium Risk", ""), IF(L23*M23>=2, IF(L23*M23<=4, "Low Risk", ""), IF(L23*M23=1, "Negligible", "")))))
C24: a. Content and categories of his or her personal data
C25: b. Sources from which personal data was obtained, if not collected from the data subject
C26: c. Purposes of processing
C27: d. Manner by which personal data were processed
C28: e. Automated processes using personal data as the sole basis for decisions that significantly impact the data subject (if applicable)
C29: f. Names and addresses of recipients of the personal data (if applicable)
C30: g. Date when his or her personal data were last accessed and modified | F30: FALSE
C31: h. Retention period
C32: i. Designation, name or identity, and address of the DPO
B33: Right to rectify (Excludes cases requiring a court order, government agency directive, or official legal process)
B34: 1 | C34: Does the data subject have the right to dispute inaccuracies in their personal data and have the PIC correct them within the reasonable time? | I34: =IF(F34="No", "Not allowing data subjects to dispute inaccuracies and correct their personal data within a reasonable time increases the risk of decisions based on incorrect information, leading to potential harm and non-compliance with data accuracy requirements.", "") | J34: =IF(F34="No", " Violation of data subject rights - Right to rectification Violation of general privacy principles – Accuracy ","") | K34: =IF(F34="No", " SEC. 16(d), DPA SEC. 11, DPA ", "") | L34: =IF(AND(F34="No", 'P1 Threshold Analysis'!D5="Yes"), 4, IF(AND(F34="No", 'P1 Threshold Analysis'!D4="Yes"),3,"")) | M34: =IF(AND(F34="No", 'P1 Threshold Analysis'!D5="Yes"), 4, IF(AND(F34="No", 'P1 Threshold Analysis'!D4="Yes"),3,"")) | N34: =IF(OR(L34="", M34=""), "", IF(L34*M34>=10, IF(L34*M34<=16, "High Risk", ""), IF(L34*M34>=6, IF(L34*M34<=9, "Medium Risk", ""), IF(L34*M34>=2, IF(L34*M34<=4, "Low Risk", ""), IF(L34*M34=1, "Negligible", "")))))
B35: 2 | C35: If personal data has been corrected,
C36: a. Does the PIC ensure that both the new and retracted information are accessible and received simultaneously by the intended recipients? | I36: =IF(OR(F36="No", F37="No"), "Failing to ensure that both corrected and retracted personal data are promptly shared with intended recipients increases the risk of data inconsistencies, leading to potential miscommunication or incorrect decision-making. ", "") | J36: =IF(OR(F36="No", F37="No"), " Violation of data subject rights - Right to rectification Violation of general privacy principles – Accuracy ","") | K36: =IF(OR(F36="No", F37="No"), " SEC. 16(d), DPA SEC. 11, DPA ", "") | L36: =IF(AND(OR(F36="No", F37="No"), 'P1 Threshold Analysis'!D5="Yes"), 4, IF(AND(OR(F36="No", F37="No"), 'P1 Threshold Analysis'!D4="Yes"), 3, "")) | M36: =IF(AND(OR(F36="No", F37="No"), 'P1 Threshold Analysis'!D5="Yes"), 4, IF(AND(OR(F36="No", F37="No"), 'P1 Threshold Analysis'!D4="Yes"), 3, "")) | N36: =IF(OR(L36="", M36=""), "", IF(L36*M36>=10, IF(L36*M36<=16, "High Risk", ""), IF(L36*M36>=6, IF(L36*M36<=9, "Medium Risk", ""), IF(L36*M36>=2, IF(L36*M36<=4, "Low Risk", ""), IF(L36*M36=1, "Negligible", ""))))) | AZ36: Failing to ensure that both corrected and retracted personal data are promptly shared with intended recipients increases the risk of data inconsistencies, leading to potential miscommunication or incorrect decision-making. Not informing recipients or third parties about corrected inaccuracies in personal data creates a risk of continued misuse or reliance on outdated information, violating data accuracy principles.
C37: b. Does the PIC inform recipients or third parties who previously received the inaccurate personal data about its inaccuracy and subsequent correction? | I37: =IF(OR(F36="No", F37="No"), "Not informing recipients or third parties about corrected inaccuracies in personal data creates a risk of continued misuse or reliance on outdated information, violating data accuracy principles. ", "") | L37: =IF(AND(OR(F36="No", F37="No"), 'P1 Threshold Analysis'!D5="Yes"), 4, IF(AND(OR(F36="No", F37="No"), 'P1 Threshold Analysis'!D4="Yes"), 3, "")) | M37: =IF(AND(OR(F36="No", F37="No"), 'P1 Threshold Analysis'!D5="Yes"), 4, IF(AND(OR(F36="No", F37="No"), 'P1 Threshold Analysis'!D4="Yes"), 3, "")) | N37: =IF(OR(L37="", M37=""), "", IF(L37*M37>=10, IF(L37*M37<=16, "High Risk", ""), IF(L37*M37>=6, IF(L37*M37<=9, "Medium Risk", ""), IF(L37*M37>=2, IF(L37*M37<=4, "Low Risk", ""), IF(L37*M37=1, "Negligible", "")))))
B38: Right to erasure or blocking
B39: 1 | C39: Does the data subject have the right to request the suspension, withdrawal, blocking, removal, or destruction of their personal data from the PIC’s live and backup systems upon discovery and substantial proof of the following? Note: Personal data is: a. Incomplete, outdated, false, or unlawfully obtained b. Used for unauthorized purpose c. No longer necessary for the purpose for which they were collected d. Prejudicial to the data subject, unless justified by freedom of speech, of expression, or of the press, or otherwise authorized | I39: =IF(F39="No", "Denying data subjects the right to request suspension or deletion of their personal data limits their control over their information and exposes the organization to non-compliance with data protection and retention obligations.", "") | J39: =IF(F39="No", " Violation of data subject rights - Right to erasure or blocking ","") | K39: =IF(F39="No", " SEC. 16(e), DPA ", "") | L39: =IF(AND(F39="No", 'P1 Threshold Analysis'!D5="Yes"), 4, IF(AND(F39="No", 'P1 Threshold Analysis'!D4="Yes"),3,"")) | M39: =IF(AND(F39="No", 'P1 Threshold Analysis'!D5="Yes"), 4, IF(AND(F39="No", 'P1 Threshold Analysis'!D4="Yes"),3,"")) | N39: =IF(OR(L39="", M39=""), "", IF(L39*M39>=10, IF(L39*M39<=16, "High Risk", ""), IF(L39*M39>=6, IF(L39*M39<=9, "Medium Risk", ""), IF(L39*M39>=2, IF(L39*M39<=4, "Low Risk", ""), IF(L39*M39=1, "Negligible", "")))))
B40: Right to data portability (Applicable if processing is based on consent or contract AND processed electronically)
B41: 1 | C41: Does the data subject have the right to obtain a copy of their personal data from the PIC and have it transmitted to another PIC in a commonly used, structured, and electronic format? | I41: =IF(F41="No", "The lack of a process to provide data subjects with their personal data in a portable, structured format increases the risk of non-compliance with data portability requirements and limits data subjects' control over their data. ", "") | J41: =IF(F41="No", " Violation of data subject rights - Right to data portability ","") | K41: =IF(F41="No", " SEC. 18, DPA ", "") | L41: =IF(AND(F41="No", 'P1 Threshold Analysis'!D5="Yes"), 4, IF(AND(F41="No", 'P1 Threshold Analysis'!D4="Yes"),3,"")) | M41: =IF(AND(F41="No", 'P1 Threshold Analysis'!D5="Yes"), 4, IF(AND(F41="No", 'P1 Threshold Analysis'!D4="Yes"),3,"")) | N41: =IF(OR(L41="", M41=""), "", IF(L41*M41>=10, IF(L41*M41<=16, "High Risk", ""), IF(L41*M41>=6, IF(L41*M41<=9, "Medium Risk", ""), IF(L41*M41>=2, IF(L41*M41<=4, "Low Risk", ""), IF(L41*M41=1, "Negligible", "")))))
B42: Right to file a complaint / damages
B43: 1 | C43: Do you inform the data subject that they have the right to file a complaint with the NPC or be indemnified for damages caused by inaccurate, incomplete, outdated, false, unlawfully obtained, or unauthorized use of their personal data? | I43: =IF(F43="No", "Failure to inform data subjects about their right to file complaints or seek indemnification may result in non-compliance with transparency obligations, leaving data subjects unaware of their rights and reducing accountability for data misuse. ", "") | J43: =IF(F43="No", " Violation of data subject rights - Right to damages ","") | K43: =IF(F43="No", " SEC. 16(f), DPA ", "") | L43: =IF(AND(F43="No", 'P1 Threshold Analysis'!D5="Yes"), 4, IF(AND(F43="No", 'P1 Threshold Analysis'!D4="Yes"),3,"")) | M43: =IF(AND(F43="No", 'P1 Threshold Analysis'!D5="Yes"), 4, IF(AND(F43="No", 'P1 Threshold Analysis'!D4="Yes"),3,"")) | N43: =IF(OR(L43="", M43=""), "", IF(L43*M43>=10, IF(L43*M43<=16, "High Risk", ""), IF(L43*M43>=6, IF(L43*M43<=9, "Medium Risk", ""), IF(L43*M43>=2, IF(L43*M43<=4, "Low Risk", ""), IF(L43*M43=1, "Negligible", "")))))

Sheet P3 Data Security
B2: Organizational Security
B3: No. | C3: Questions | F3: Yes/No/N/A | H3: Response | I3: Threats/Vulnerabilities | J3: Risk | K3: Legal Basis | L3: Impact | M3: Probability | N3: Risk Rating
B4: 1 | C4: Have you appointed and registered a data protection officer (DPO) with the National Privacy Commission (NPC)? | I4: =IF(F4="No", "The absence of a registered DPO exposes the organization to a lack of oversight and accountability in managing data protection practices, increasing the risk of non-compliance with privacy regulations and potential legal penalties.", "") | J4: =IF(F4="No", "Failure to implement reasonable and appropriate security measures - Organizational ","") | K4: =IF(F4="No", "SEC. 20, DPA", "") | L4: =IF(AND(F4="No", 'P1 Threshold Analysis'!D5="Yes"), 4, IF(AND(F4="No", 'P1 Threshold Analysis'!D4="Yes"),3,"")) | M4: =IF(AND(F4="No", 'P1 Threshold Analysis'!D5="Yes"), 4, IF(AND(F4="No", 'P1 Threshold Analysis'!D4="Yes"),3,"")) | N4: =IF(OR(L4="", M4=""), "", IF(L4*M4>=10, IF(L4*M4<=16, "High Risk", ""), IF(L4*M4>=6, IF(L4*M4<=9, "Medium Risk", ""), IF(L4*M4>=2, IF(L4*M4<=4, "Low Risk", ""), IF(L4*M4=1, "Negligible", "")))))
B5: 2 | C5: Have you registered this project or system with the NPC? | I5: =IF(F5="No", "Failure to register the project or system with the NPC makes the organization non-compliant, risking administrative fines. ", "") | J5: =IF(F5="No", "Failure to implement reasonable and appropriate security measures – Organizational Failure to register the data processing system ","") | K5: =IF(F5="No", "SEC 20, DPA SEC. 24, DPA ", "") | L5: =IF(AND(F5="No", 'P1 Threshold Analysis'!D5="Yes"), 4, IF(AND(F5="No", 'P1 Threshold Analysis'!D4="Yes"),3,"")) | M5: =IF(AND(F5="No", 'P1 Threshold Analysis'!D5="Yes"), 4, IF(AND(F5="No", 'P1 Threshold Analysis'!D4="Yes"),3,"")) | N5: =IF(OR(L5="", M5=""), "", IF(L5*M5>=10, IF(L5*M5<=16, "High Risk", ""), IF(L5*M5>=6, IF(L5*M5<=9, "Medium Risk", ""), IF(L5*M5>=2, IF(L5*M5<=4, "Low Risk", ""), IF(L5*M5=1, "Negligible", "")))))
B6: 3 | C6: Do you have an inventory of this project or system? Check all present | I6: =IF(F6="No", "The absence of an inventory for a project or system prevents the organization from effectively managing personal data processing activities, increasing the risk of unauthorized access, data breaches, and non-compliance with data protection laws.", "") | J6: =IF(F6="No", "Failure to implement reasonable and appropriate security measures – Organizational Personal Data Breach - Availability ","") | K6: =IF(F6="No", "SEC 20, DPA ", "") | L6: =IF(AND(F6="No", COUNTIF(F7:G11, "False")>4), 4, IF(AND(F6="No", 'P1 Threshold Analysis'!D5="Yes", COUNTIF(F7:G11, "True")>0), 4, IF(AND(F6="No", 'P1 Threshold Analysis'!D5="No",COUNTIF(F7:G11, "True")>0), 3, ""))) | M6: =IF(AND(F6="No", COUNTIF(F7:G11, "False")>4), 4, IF(AND(F6="No", 'P1 Threshold Analysis'!D5="Yes", COUNTIF(F7:G11, "True")>0), 4, IF(AND(F6="No", 'P1 Threshold Analysis'!D5="No",COUNTIF(F7:G11, "True")>0), 3, ""))) | N6: =IF(OR(L6="", M6=""), "", IF(L6*M6>=10, IF(L6*M6<=16, "High Risk", ""), IF(L6*M6>=6, IF(L6*M6<=9, "Medium Risk", ""), IF(L6*M6>=2, IF(L6*M6<=4, "Low Risk", ""), IF(L6*M6=1, "Negligible", ""))))) | AZ6: The absence of an inventory for the project or system prevents the organization from effectively managing and monitoring personal data processing activities, increasing the risk of unauthorized access, data breaches, and non-compliance with data protection laws.
C7: a. Purpose of processing of personal data, including future processing or data sharing. | F7: FALSE
C8: b. Categories of data subjects, personal data, and recipients involved. | F8: FALSE
C9: c. Data flow from collection to disposal, including retention periods. | F9: FALSE
C10: d. Security measures (organizational, physical, and technical) | F10: FALSE
C11: e. Contacts details of the PIC, joint controller (if applicable), representative, and compliance officer or DPO. | F11: FALSE
B12: 4 | C12: Do you conduct a PIA for this project or system annually and update it when necessary (e.g., new features, major changes, new regulations, new contracts entered), considering the minimum requirements? Check all present | I12: =IF(F12="No", "Not conducting an annual PIA or updating it as needed increases the likelihood of overlooking new risks, vulnerabilities, or changes in processing activities, potentially leading to non-compliance and inadequate protection of personal data. ", "") | J12: =IF(F12="No", "Failure to implement reasonable and appropriate security measures – Organizational ","") | K12: =IF(F12="No", "SEC. 20, DPA ", "") | L12: =IF(AND(F12="No", COUNTIF(C14:H29, "False")>13), 4, IF(AND(F12="No", 'P1 Threshold Analysis'!D5="Yes", COUNTIF(C14:H29, "True")>0), 4, IF(AND(F12="No", 'P1 Threshold Analysis'!D5="No",COUNTIF(C14:H29, "True")>0), 3, ""))) | M12: =IF(AND(F12="No", COUNTIF(C14:H29, "False")>13), 4, IF(AND(F12="No", 'P1 Threshold Analysis'!D5="Yes", COUNTIF(C14:H29, "True")>0), 4, IF(AND(F12="No", 'P1 Threshold Analysis'!D5="No",COUNTIF(C14:H29, "True")>0), 3, ""))) | N12: =IF(OR(L12="", M12=""), "", IF(L12*M12>=10, IF(L12*M12<=16, "High Risk", ""), IF(L12*M12>=6, IF(L12*M12<=9, "Medium Risk", ""), IF(L12*M12>=2, IF(L12*M12<=4, "Low Risk", ""), IF(L12*M12=1, "Negligible", "")))))
C13: a. Data inventory
C14: i. Types and volume of personal data held, including employee records | F14: FALSE
C15: ii. List and location of repositories of personal data | F15: FALSE
C16: iii. Storage media used | F16: FALSE
C17: iv. Risks associated with data processing | F17: FALSE
C18: v. Processing operations across the data lifecycle, from collection to disposal | F18: FALSE
C19: b. Systematic Description | F19: FALSE
C20: c. Assessment of:
C21: i. General Data Privacy Principles | F21: FALSE
C22: ii. Rights and freedoms of a data subject | F22: FALSE
C23: iii. Data Security/confidentiality, integrity, and availability | F23: FALSE
C24: d. Risks identified are addressed by a Control Framework
C25: i. Nature of the personal data being protected | F25: FALSE
C26: ii. Risks from processing, organization size, and data volume | F26: FALSE
C27: iii. Industry best practices for data privacy | F27: FALSE
C28: iv. Cost of implementing security measures | F28: FALSE
C29: v. Purpose, scope, and risks of data sharing or outsourcing agreements | F29: FALSE
B30: 5 | C30: Are the personnel who process personal data under strict confidentiality if personal data are not intended for public disclosure (signing of NDAs)? | I30: =IF(F30="No", "Without strict confidentiality agreements (NDAs) in place, personnel may inadvertently disclose personal data, exposing the organization to data breaches and violating privacy obligations. ", "") | J30: =IF(F30="No", "Failure to implement reasonable and appropriate security measures – Organizational Personal Data Breach - Confidentiality ","") | K30: =IF(F30="No", "SEC. 20, DPA ", "") | L30: =IF(AND(F30="No", 'P1 Threshold Analysis'!D5="Yes"), 4, IF(AND(F30="No", 'P1 Threshold Analysis'!D4="Yes"),3,"")) | M30: =IF(AND(F30="No", 'P1 Threshold Analysis'!D5="Yes"), 4, IF(AND(F30="No", 'P1 Threshold Analysis'!D4="Yes"),3,"")) | N30: =IF(OR(L30="", M30=""), "", IF(L30*M30>=10, IF(L30*M30<=16, "High Risk", ""), IF(L30*M30>=6, IF(L30*M30<=9, "Medium Risk", ""), IF(L30*M30>=2, IF(L30*M30<=4, "Low Risk", ""), IF(L30*M30=1, "Negligible", "")))))
B31: 6 | C31: Do you periodically train employees, agents, personnel, or representatives on privacy and data protection policies? | I31: =IF(F31="No", "The lack of periodic training on privacy and data protection policies increases the risk of employees inadvertently violating data protection regulations or mishandling personal data, potentially leading to data breaches or non-compliance.", "") | J31: =IF(F31="No", "Failure to implement reasonable and appropriate security measures – Organizational ","") | K31: =IF(F31="No", "SEC. 20, DPA ", "") | L31: =IF(AND(F31="No", 'P1 Threshold Analysis'!D5="Yes"), 4, IF(AND(F31="No", 'P1 Threshold Analysis'!D4="Yes"),3,"")) | M31: =IF(AND(F31="No", 'P1 Threshold Analysis'!D5="Yes"), 4, IF(AND(F31="No", 'P1 Threshold Analysis'!D4="Yes"),3,"")) | N31: =IF(OR(L31="", M31=""), "", IF(L31*M31>=10, IF(L31*M31<=16, "High Risk", ""), IF(L31*M31>=6, IF(L31*M31<=9, "Medium Risk", ""), IF(L31*M31>=2, IF(L31*M31<=4, "Low Risk", ""), IF(L31*M31=1, "Negligible", "")))))
B32: 7 | C32: Do you have a Privacy Management Program (PMP) in place that considers the following? Check all present | I32: =IF(F32="No", "The absence of a PMP leaves the organization without a structured approach to ensure ongoing compliance, risk mitigation, and effective handling of personal data, increasing the likelihood of non-compliance and privacy violations.", "") | J32: =IF(F32="No", "Failure to implement reasonable and appropriate security measures – Organizational ","") | K32: =IF(F32="No", "SEC. 20, DPA ", "") | L32: =IF(AND(F32="No", COUNTIF(C34:H50, "False")>14), 4, IF(AND(F32="No", 'P1 Threshold Analysis'!D5="Yes", COUNTIF(C34:H50, "True")>0), 4, IF(AND(F32="No", 'P1 Threshold Analysis'!D5="No",COUNTIF(C34:H50, "True")>0), 3, ""))) | M32: =IF(AND(F32="No", COUNTIF(C34:H50, "False")>14), 4, IF(AND(F32="No", 'P1 Threshold Analysis'!D5="Yes", COUNTIF(C34:H50, "True")>0), 4, IF(AND(F32="No", 'P1 Threshold Analysis'!D5="No",COUNTIF(C34:H50, "True")>0), 3, ""))) | N32: =IF(OR(L32="", M32=""), "", IF(L32*M32>=10, IF(L32*M32<=16, "High Risk", ""), IF(L32*M32>=6, IF(L32*M32<=9, "Medium Risk", ""), IF(L32*M32>=2, IF(L32*M32<=4, "Low Risk", ""), IF(L32*M32=1, "Negligible", "")))))
C33: a. Organizational Commitment and leadership in data privacy.
C34: i. Management Buy-In | F34: FALSE
C35: ii. Data Protection Officer | F35: FALSE
C36: iii. Reporting Mechanisms | F36: FALSE
C37: b. Control Framework for developing privacy policies and implementing data protection measures.
C38: iv. Records of Processing Activities (RoPA) | F38: FALSE
C39: v. Risk Assessment | F39: FALSE
C40: vi. Registration | F40: FALSE
C41: vii. Policies and Procedures | F41: FALSE
C42: viii. Data Security | F42: FALSE
C43: ix. Capacity Building | F43: FALSE
C44: x. Breach Management | F44: FALSE
C45: xi. Notification | F45: FALSE
C46: xii. Third-Party Management | F46: FALSE
C47: xiii. Communication | F47: FALSE
C48: c. Oversight and continuous improvements of controls.
C49: xiv. Develop Oversight and Review Plan | F49: FALSE
C50: xv. Updates and Revisions | F50: FALSE
B51: 8 | C51: Are there any data protection and security measure policies in place? Check all present | I51: =IF(F51="No", "The absence of data protection and security measure policies exposes the organization to increased risk of data breaches, unauthorized access, mishandling of personal data, and non-compliance with data protection regulations. ", "") | J51: =IF(F51="No", "Failure to implement reasonable and appropriate security measures – Organizational ","") | K51: =IF(F51="No", "SEC. 20, DPA ", "") | L51: =IF(AND(F51="No", COUNTIF(C53:H103, "False")>42), 4, IF(AND(F51="No", 'P1 Threshold Analysis'!D5="Yes", COUNTIF(C53:H103, "True")>0), 4, IF(AND(F51="No", 'P1 Threshold Analysis'!D5="No",COUNTIF(C53:H103, "True")>0), 3, ""))) | M51: =IF(AND(F51="No", COUNTIF(C53:H103, "False")>42), 4, IF(AND(F51="No", 'P1 Threshold Analysis'!D5="Yes", COUNTIF(C53:H103, "True")>0), 4, IF(AND(F51="No", 'P1 Threshold Analysis'!D5="No",COUNTIF(C53:H103, "True")>0), 3, ""))) | N51: =IF(OR(L51="", M51=""), "", IF(L51*M51>=10, IF(L51*M51<=16, "High Risk", ""), IF(L51*M51>=6, IF(L51*M51<=9, "Medium Risk", ""), IF(L51*M51>=2, IF(L51*M51<=4, "Low Risk", ""), IF(L51*M51=1, "Negligible", "")))))
C52: a. Privacy Manual (PM)
C53: i. Introduction | F53: FALSE
C54: ii. Definition of Terms | F54: FALSE
C55: iii. Scope and Limitations | F55: FALSE
C56: iv. Processing of Personal Data
C57: 1. Collection | F57: FALSE
C58: 2. Use | F58: FALSE
C59: 3. Storage, Retention, and Destruction | F59: FALSE
C60: 4. Access | F60: FALSE
C61: 5. Disclosure and Sharing | F61: FALSE
C62: v. Security Measures (can be a separate policy, e.g., Information Security Policy)
C63: 1. Organizational Measures
C64: a. Conduct of Privacy Impact Assessment (PIA) | F64: FALSE
C65: b. Designation and function of Data Protection Officer (DPO) and other responsible personnel | F65: FALSE
C66: c. Duty of confidentiality (signing an NDA) | F66: FALSE
C67: d. Conduct of training and seminars | F67: FALSE
C68: e. Review of PM | F68: FALSE
C69: f. Recording and documentation of activities carried out by the DPO/organization | F69: FALSE
C70: 2. Physical Measures
C71: a. Format of data to be collected | F71: FALSE | G71: FALSE
C72: b. Storage type and location | F72: FALSE | G72: FALSE
C73: c. Access Control (onsite, remote, and online) and security clearance | F73: FALSE | G73: FALSE
C74: d. Design of office space/workstation | F74: FALSE | G74: FALSE
C75: e. Duties and responsibilities of personnel involved in processing | F75: FALSE | G75: FALSE
C76: f. Mode of transfer | F76: FALSE | G76: FALSE
C77: g. Retention and Disposal Procedure | F77: FALSE | G77: FALSE
C78: 3. Technical Measures
C79: a. Monitoring for security breaches | F79: FALSE | G79: FALSE
C80: b. Security features of software and applications used | F80: FALSE | G80: FALSE
C81: c. Process for regular testing, assessment, and evaluation of security measures | F81: FALSE | G81: FALSE
C82: d. Encryption, authentication, and other technical security measures to control and limit access to personal data | F82: FALSE | G82: FALSE
C83: vi. Breach and Security Incidents (can be a separate policy, e.g., Security Incident Management Policy)
C84: 1. Creation of a Data Breach Response Team | F84: FALSE
C85: 2. Measures to prevent and mitigate breaches and security incidents | F85: FALSE
C86: 3. Incident Response Procedure | F86: FALSE
C87: 4. Records of security incidents and personal data breaches and notifications | F87: FALSE
C88: vii. Inquiries and Complaints (can be a separate policy, e.g., Data Subject and Third-Party Requests Policy) | F88: FALSE
C89: viii. Effectivity | F89: FALSE
C90: ix. Annexes
C91: 1. Privacy Notice | F91: FALSE
C92: 2. Consent Form | F92: FALSE
C93: 3. Data Outsourcing Agreement | F93: FALSE
C94: 4. Non-Disclosure Agreement | F94: FALSE
C95: 5. Security Clearance | F95: FALSE
C96: 6. Inquiry Form/Data Subject/Third Party Request Form | F96: FALSE
C97: May be in the PM or separate:
C98: x. Acceptable Use Policy | F98: FALSE
C99: xi. Password Policy | F99: FALSE
C100: xii. Business Continuity Plan | F100: FALSE
C101: xiii. Telecommuting | F101: FALSE
...

Sheet P3 Cross-border Data Flows
B2: (Optional) Cross-border Data Flows
B3: Is there any cross-border transfer of data?
B4: No. | C4: Questions | F4: Yes/No/N/A | H4: Response | I4: Threats/Vulnerabilities | J4: Risk | K4: Legal Basis | L4: Impact | M4: Probability | N4: Risk Rating
B5: 1 | C5: Does the project or system transfer personal data to an organization or individual outside the Philippines, including cloud storage or data centers? Personal data will only be transferred to someone outside of the Philippines if any of the following apply: Check all applicable | F5: No | I5: =IF(F5="No", "Transferring personal data abroad without a lawful basis may lead to unauthorized processing, data breaches, and legal penalties under data protection laws.", "") -> Transferring personal data abroad without a lawful basis may lead to unauthorized processing, data breaches, and legal penalties under data protection laws. | J5: =IF(F5="No", "Unlawful Processing - Unauthorized Processing of Personal Data Unlawful Processing - Unauthorized Disclosure ","") -> Unlawful Processing - Unauthorized Processing of Personal Data Unlawful Processing - Unauthorized Disclosure | K5: =IF(F5="No", "SEC. 25, DPA SEC. 32, DPA ", "") -> SEC. 25, DPA SEC. 32, DPA | L5: =IF(AND(F5="No", 'P1 Threshold Analysis'!D5="Yes"), 4, IF(AND(F5="No", 'P1 Threshold Analysis'!D4="Yes"),3,"")) | M5: =IF(AND(F5="No", 'P1 Threshold Analysis'!D5="Yes"), 4, IF(AND(F5="No", 'P1 Threshold Analysis'!D4="Yes"),3,"")) | N5: =IF(OR(L5="", M5=""), "", IF(L5*M5>=10, IF(L5*M5<=16, "High Risk", ""), IF(L5*M5>=6, IF(L5*M5<=9, "Medium Risk", ""), IF(L5*M5>=2, IF(L5*M5<=4, "Low Risk", ""), IF(L5*M5=1, "Negligible", "")))))
C6: a. The individual consents to the transfer | F6: FALSE
C7: b. The recipients is subject to laws or a contract enforcing information handling principles similar to the DPA of 2012. | F7: FALSE
C8: c. The transfer is necessary to fulfill a contract between the individual and the organization. | F8: FALSE
C9: d. The transfer is required for a contract in the individual’s interest between the organization and a third party | F9: FALSE
C10: e. The transfer benefits the individual. | F10: FALSE
B11: 2 | C11: Has the organization taken reasonable steps to ensure that transferred data is stored, used, disclosed, and processed in compliance with the DPA of 2012? Check all present | I11: =IF(F11="No", "Failure to ensure that cross-border data transfers comply with the Data Privacy Act of 2012 increases the risk of personal data being misused or accessed without authorization and exposes the organization to regulatory sanctions for non-compliance.", "") | J11: =IF(F11="No", "Failure to implement reasonable and appropriate security measures – Organizational Failure to ensure that third parties implement security measures Personal Data Breach - Availability, Integrity, Confidentiality ","") | K11: =IF(F11="No", "SEC. 20, DPA ", "") | L11: =IF(AND(F11="No", COUNTIF(F12:G16, "False")>4), 4, IF(AND(F11="No", 'P1 Threshold Analysis'!D5="Yes", COUNTIF(F12:G16, "True")>0), 4, IF(AND(F11="No", 'P1 Threshold Analysis'!D5="No",COUNTIF(F12:G16, "True")>0), 3, ""))) | M11: =IF(AND(F11="No", COUNTIF(F12:G16, "False")>4), 4, IF(AND(F11="No", 'P1 Threshold Analysis'!D5="Yes", COUNTIF(F12:G16, "True")>0), 4, IF(AND(F11="No", 'P1 Threshold Analysis'!D5="No",COUNTIF(F12:G16, "True")>0), 3, ""))) | N11: =IF(OR(L11="", M11=""), "", IF(L11*M11>=10, IF(L11*M11<=16, "High Risk", ""), IF(L11*M11>=6, IF(L11*M11<=9, "Medium Risk", ""), IF(L11*M11>=2, IF(L11*M11<=4, "Low Risk", ""), IF(L11*M11=1, "Negligible", "")))))
C12: a. Data Transfer Security (e.g., lawful basis, data sharing/outsourcing agreements, secure transmission methods – TLS 1.2/1.3, VPN, data minimization) | F12: FALSE
C13: b. Data Storage & Protection (e.g., encryption of data at rest/AES-256, access control & role-based permissions, secure physical & cloud storage, data retention & disposal policies) | F13: FALSE
C14: c. Data Usage & Processing Compliance (e.g., purpose limitation, regular data processing audit, anonymization & pseudonymization, consent management) | F14: FALSE
C15: d. Data Disclosure Controls (e.g., strict third-party sharing rules, confidentiality agreements, data subject access & correction rights, data breach notification procedures) | F15: FALSE
C16: e. Compliance, Monitoring & Awareness (e.g., PIA, appointment of a DPO, Employee Privacy Training, Incident Response Plan) | F16: FALSE

Sheet Risk Treatment Plan
B2: Observation (Threat/Vulnerability) | C2: Risk | D2: Inherent Risk | E2: Risk Treatment | F2: Mitigation Measure | G2: Status | H2: Residual Risk Rating | I2: Control Reference | J2: Start Date | K2: Completion Date | L2: Review Frequency | M2: Risk Owner
B3: {=_xlfn.LET( _xlpm.combined, _xlfn.UNIQUE( _xlfn.VSTACK( IFERROR(_xlfn._xlws.FILTER(CHOOSE({1,2}, 'P3 Gen Data Privacy Principles'!H7:H18, 'P3 Gen Data Privacy Principles'!I7:I18), 'P3 Gen Data Privacy Principles'!H7:H18<>""), ""), IFERROR(_xlfn._xlws.FILTER(CHOOSE({1,2}, 'P3 Gen Data Privacy Principles'!H20:H21, 'P3 Gen Data Privacy Principles'!I20:I21), 'P3 Gen Data Privacy Principles'!H20:H21<>""), ""), IFERROR(_xlfn._xlws.FILTER(CHOOSE({1,2}, 'P3 Gen Data Privacy Principles'!H24:H28, 'P3 Gen Data Privacy Principles'!I24:I28), 'P3 Gen Data Privacy Principles'!H24:H28<>""), ""), IFERROR(_xlfn._xlws.FILTER(CHOOSE({1,2}, 'P3 Gen Data Privacy Principles'!H30, 'P3 Gen Data Privacy Principles'!I30), 'P3 Gen Data Privacy Principles'!H30<>""), ""), IFERROR(_xlfn._xlws.FILTER(CHOOSE({1,2}, 'P3 Gen Data Privacy Principles'!H32:H40, 'P3 Gen Data Privacy Principles'!I32:I40), 'P3 Gen Data Privacy Principles'!H32:H40<>""), ""), IFERROR(_xlfn._xlws.FILTER(CHOOSE({1,2}, 'P3 Gen Data Privacy Principles'!H42, 'P3 Gen Data Privacy Principles'!I42), 'P3 Gen Data Privacy Principles'!H42<>""), ""), IFERROR(_xlfn._xlws.FILTER(CHOOSE({1,2}, 'P3 Gen Data Privacy Principles'!H44, 'P3 Gen Data Privacy Principles'!I44), 'P3 Gen Data Privacy Principles'!H44<>""), ""), IFERROR(_xlfn._xlws.FILTER(CHOOSE({1,2}, 'P3 Data Subject Rights'!I11:I21, 'P3 Data Subject Rights'!J11:J21), 'P3 Data Subject Rights'!I11:I21<>""), ""), IFERROR(_xlfn._xlws.FILTER(CHOOSE({1,2}, 'P3 Data Subject Rights'!I23, 'P3 Data Subject Rights'!J23), 'P3 Data Subject Rights'!I23<>""), ""), IFERROR(_xlfn._xlws.FILTER(CHOOSE({1,2}, 'P3 Data Subject Rights'!I34, 'P3 Data Subject Rights'!J34), 'P3 Data Subject Rights'!I34<>""), ""), IFERROR(_xlfn._xlws.FILTER(CHOOSE({1,2},'P3 Data Subject Rights'!I36, 'P3 Data Subject Rights'!J36), 'P3 Data Subject Rights'!I36<>""), ""), IFERROR(_xlfn._xlws.FILTER(CHOOSE({1,2},'P3 Data Subject Rights'!I37, 'P3 Data Subject Rights'!J36), 'P3 Data Subject Rights'!I37<>""), ""), IFERROR(_xlfn._xlws.FILTER(CHOOSE({1,2}, 'P3 Data Subject Rights'!I39, 'P3 Data Subject Rights'!J39), 'P3 Data Subject Rights'!I39<>""), ""), IFERROR(_xlfn._xlws.FILTER(CHOOSE({1,2},'P3 Data Subject Rights'!I41, 'P3 Data Subject Rights'!J41), 'P3 Data Subject Rights'!I41<>""), ""), IFERROR(_xlfn._xlws.FILTER(CHOOSE({1,2},'P3 Data Subject Rights'!I43, 'P3 Data Subject Rights'!J43), 'P3 Data Subject Rights'!I43<>""), ""), IFERROR(_xlfn._xlws.FILTER(CHOOSE({1,2},'P3 Data Security'!I4,'P3 Data Security'!J4), 'P3 Data Security'!I4<>""), ""), IFERROR(_xlfn._xlws.FILTER(CHOOSE({1,2},'P3 Data Security'!I5,'P3 Data Security'!J5), 'P3 Data Security'!I5<>""), ""), IFERROR(_xlfn._xlws.FILTER(CHOOSE({1,2},'P3 Data Security'!I6,'P3 Data Security'!J6), 'P3 Data Security'!I6<>""), ""), IFERROR(_xlfn._xlws.FILTER(CHOOSE({1,2},'P3 Data Security'!I12,'P3 Data Security'!J12), 'P3 Data Security'!I12<>""), ""), IFERROR(_xlfn._xlws.FILTER(CHOOSE({1,2},'P3 Data Security'!I30,'P3 Data Security'!J30), 'P3 Data Security'!I30<>""), ""), IFERROR(_xlfn._xlws.FILTER(CHOOSE({1,2},'P3 Data Security'!I31,'P3 Data Security'!J31), 'P3 Data Security'!I31<>""), ""), IFERROR(_xlfn._xlws.FILTER(CHOOSE({1,2},'P3 Data Security'!I32,'P3 Data Security'!J32), 'P3 Data Security'!I32<>""), ""), IFERROR(_xlfn._xlws.FILTER(CHOOSE({1,2},'P3 Data Security'!I51,'P3 Data Security'!J51), 'P3 Data Security'!I51<>""), ""), IFERROR(_xlfn._xlws.FILTER(CHOOSE({1,2},'P3 Data Security'!I104,'P3 Data Security'!J104), 'P3 Data Security'!I104<>""), ""), IFERROR(_xlfn._xlws.FILTER(CHOOSE({1,2},'P3 Data Security'!I121,'P3 Data Security'!J121), 'P3 Data Security'!I121<>""), ""), IFERROR(_xlfn._xlws.FILTER(CHOOSE({1,2},'P3 Data Security'!I129,'P3 Data Security'!J129), 'P3 Data Security'!I129<>""), ""), IFERROR(_xlfn._xlws.FILTER(CHOOSE({1,2},'P3 Data Security'!I134,'P3 Data Security'!J134), 'P3 Data Security'!I134<>""), ""), IFERROR(_xlfn._xlws.FILTER(CHOOSE({1,2},'P3 Data Security'!I135,'P3 Data Security'!J135), 'P3 Data Security'!I135<>""), ""), IFERROR(_xlfn._xlws.FILTER(CHOOSE({1,2},'P3 Data Security'!I136,'P3 Data Security'!J136), 'P3 Data Security'!I136<>""), ""), IFERROR(_xlfn._xlws.FILTER(CHOOSE({1,2},'P3 Data Security'!I144,'P3 Data Security'!J144), 'P3 Data Security'!I144<>""), ""), IFERROR(_xlfn._xlws.FILTER(CHOOSE({1,2},'P3 Data Security'!I151,'P3 Data Security'!J151), 'P3 Data Security'!I151<>""), ""), IFERROR(_xlfn._xlws.FILTER(CHOOSE({1,2},'P3 Data Security'!I152,'P3 Data Security'!J152), 'P3 Data Security'!I152<>""), ""), IFERROR(_xlfn._xlws.FILTER(CHOOSE({1,2},'P3 Data Security'!I153,'P3 Data Security'!J153), 'P3 Data Security'!I153<>""), ""), IFERROR(_xlfn._xlws.FILTER(CHOOSE({1,2},'P3 Cross-border Data Flows'!I5,'P3 Cross-border Data Flows'!J5),'P3 Cross-border Data Flows'!I5<>""), ""), IFERROR(_xlfn._xlws.FILTER(CHOOSE({1,2},'P3 Cross-border Data Flows'!I11,'P3 Cross-border Data Flows'!J11),'P3 Cross-border Data Flows'!I11<>""), "") ) ), _xlfn._xlws.FILTER(_xlpm.combined, (TRIM(INDEX(_xlpm.combined,,1))<>"") * (INDEX(_xlpm.combined,,1)<>"N/A")) )} -> Transferring personal data abroad without a lawful basis may lead to unauthorized processing, data breaches, and legal penalties under data protection laws. | C3: Unlawful Processing - Unauthorized Processing of Personal Data Unlawful Processing - Unauthorized Disclosure | D3: =_xlfn.XLOOKUP(B3,'Mitigation Map'!H:H,'Mitigation Map'!M:M, "") | E3: =_xlfn.XLOOKUP(F3,'Mitigation Map'!O:O,'Mitigation Map'!N:N,"") -> Reduce | F3: =_xlfn.XLOOKUP(B3,'Mitigation Map'!H:H, 'Mitigation Map'!O:O, "No Mitigation Found") -> Prior to any cross-border transfer of personal data, the organization shall ensure that such transfers are grounded on a lawful basis under the Data Privacy Act of 2012. Only countries with adequate protection, contractual safeguards, or a specific legal basis (e.g., consent, contract, or international agreements) will be permitted as data transfer destinations. The Data Protection Officer will maintain records of all cross-border transfers, and contracts entered into. | G3: =_xlfn.XLOOKUP(F3,'Mitigation Map'!O:O,'Mitigation Map'!P:P,"") -> Planned | H3: =_xlfn.XLOOKUP(F3,'Mitigation Map'!O:O,'Mitigation Map'!Q:Q) -> Low | I3: =_xlfn.XLOOKUP(F3,'Mitigation Map'!O:O, 'Mitigation Map'!R:R, "") -> SECS. 21, 22, 50, IRR | J3: 45880 | K3: =IF(OR(J3="", _xlfn.XLOOKUP('Risk Treatment Plan'!F3, 'Mitigation Map'!O:O, 'Mitigation Map'!T:T, "")=""), "", J3 + _xlfn.XLOOKUP('Risk Treatment Plan'!F3, 'Mitigation Map'!O:O, 'Mitigation Map'!T:T)) -> 45881 | L3: =_xlfn.XLOOKUP(F3,'Mitigation Map'!O:O,'Mitigation Map'!U:U,"") -> Annual or upon any significant change to data processing activities | M3: =_xlfn.XLOOKUP(F3,'Mitigation Map'!O:O,'Mitigation Map'!V:V,"") -> System/Process Owner
D4: =_xlfn.XLOOKUP(B4,'Mitigation Map'!H:H,'Mitigation Map'!M:M, "") -> 0 | E4: =_xlfn.XLOOKUP(F4,'Mitigation Map'!O:O,'Mitigation Map'!N:N,"") | F4: =_xlfn.XLOOKUP(B4,'Mitigation Map'!H:H, 'Mitigation Map'!O:O, "No Mitigation Found") -> 0 | G4: =_xlfn.XLOOKUP(F4,'Mitigation Map'!O:O,'Mitigation Map'!P:P,"") | H4: =_xlfn.XLOOKUP(F4,'Mitigation Map'!O:O,'Mitigation Map'!Q:Q) -> #N/A | I4: =_xlfn.XLOOKUP(F4,'Mitigation Map'!O:O, 'Mitigation Map'!R:R, "") | J4: =IF(OR($J$3="", F4=""), "", $J$3) -> 45880 | K4: =IF(OR(J4="", _xlfn.XLOOKUP('Risk Treatment Plan'!F4, 'Mitigation Map'!O:O, 'Mitigation Map'!T:T, "")=""), "", J4 + _xlfn.XLOOKUP('Risk Treatment Plan'!F4, 'Mitigation Map'!O:O, 'Mitigation Map'!T:T)) | L4: =_xlfn.XLOOKUP(F4,'Mitigation Map'!O:O,'Mitigation Map'!U:U,"") | M4: =_xlfn.XLOOKUP(F4,'Mitigation Map'!O:O,'Mitigation Map'!V:V,"")
D5: =_xlfn.XLOOKUP(B5,'Mitigation Map'!H:H,'Mitigation Map'!M:M, "") -> 0 | E5: =_xlfn.XLOOKUP(F5,'Mitigation Map'!O:O,'Mitigation Map'!N:N,"") | F5: =_xlfn.XLOOKUP(B5,'Mitigation Map'!H:H, 'Mitigation Map'!O:O, "No Mitigation Found") -> 0 | G5: =_xlfn.XLOOKUP(F5,'Mitigation Map'!O:O,'Mitigation Map'!P:P,"") | H5: =_xlfn.XLOOKUP(F5,'Mitigation Map'!O:O,'Mitigation Map'!Q:Q) -> #N/A | I5: =_xlfn.XLOOKUP(F5,'Mitigation Map'!O:O, 'Mitigation Map'!R:R, "") | J5: =IF(OR($J$3="", F5=""), "", $J$3) -> 45880 | K5: =IF(OR(J5="", _xlfn.XLOOKUP('Risk Treatment Plan'!F5, 'Mitigation Map'!O:O, 'Mitigation Map'!T:T, "")=""), "", J5 + _xlfn.XLOOKUP('Risk Treatment Plan'!F5, 'Mitigation Map'!O:O, 'Mitigation Map'!T:T)) | L5: =_xlfn.XLOOKUP(F5,'Mitigation Map'!O:O,'Mitigation Map'!U:U,"") | M5: =_xlfn.XLOOKUP(F5,'Mitigation Map'!O:O,'Mitigation Map'!V:V,"")
D6: =_xlfn.XLOOKUP(B6,'Mitigation Map'!H:H,'Mitigation Map'!M:M, "") -> 0 | E6: =_xlfn.XLOOKUP(F6,'Mitigation Map'!O:O,'Mitigation Map'!N:N,"") | F6: =_xlfn.XLOOKUP(B6,'Mitigation Map'!H:H, 'Mitigation Map'!O:O, "No Mitigation Found") -> 0 | G6: =_xlfn.XLOOKUP(F6,'Mitigation Map'!O:O,'Mitigation Map'!P:P,"") | H6: =_xlfn.XLOOKUP(F6,'Mitigation Map'!O:O,'Mitigation Map'!Q:Q) -> #N/A | I6: =_xlfn.XLOOKUP(F6,'Mitigation Map'!O:O, 'Mitigation Map'!R:R, "") | J6: =IF(OR($J$3="", F6=""), "", $J$3) -> 45880 | K6: =IF(OR(J6="", _xlfn.XLOOKUP('Risk Treatment Plan'!F6, 'Mitigation Map'!O:O, 'Mitigation Map'!T:T, "")=""), "", J6 + _xlfn.XLOOKUP('Risk Treatment Plan'!F6, 'Mitigation Map'!O:O, 'Mitigation Map'!T:T)) | L6: =_xlfn.XLOOKUP(F6,'Mitigation Map'!O:O,'Mitigation Map'!U:U,"") | M6: =_xlfn.XLOOKUP(F6,'Mitigation Map'!O:O,'Mitigation Map'!V:V,"")
D7: =_xlfn.XLOOKUP(B7,'Mitigation Map'!H:H,'Mitigation Map'!M:M, "") -> 0 | E7: =_xlfn.XLOOKUP(F7,'Mitigation Map'!O:O,'Mitigation Map'!N:N,"") | F7: =_xlfn.XLOOKUP(B7,'Mitigation Map'!H:H, 'Mitigation Map'!O:O, "No Mitigation Found") -> 0 | G7: =_xlfn.XLOOKUP(F7,'Mitigation Map'!O:O,'Mitigation Map'!P:P,"") | H7: =_xlfn.XLOOKUP(F7,'Mitigation Map'!O:O,'Mitigation Map'!Q:Q) -> #N/A | I7: =_xlfn.XLOOKUP(F7,'Mitigation Map'!O:O, 'Mitigation Map'!R:R, "") | J7: =IF(OR($J$3="", F7=""), "", $J$3) -> 45880 | K7: =IF(OR(J7="", _xlfn.XLOOKUP('Risk Treatment Plan'!F7, 'Mitigation Map'!O:O, 'Mitigation Map'!T:T, "")=""), "", J7 + _xlfn.XLOOKUP('Risk Treatment Plan'!F7, 'Mitigation Map'!O:O, 'Mitigation Map'!T:T)) | L7: =_xlfn.XLOOKUP(F7,'Mitigation Map'!O:O,'Mitigation Map'!U:U,"") | M7: =_xlfn.XLOOKUP(F7,'Mitigation Map'!O:O,'Mitigation Map'!V:V,"")
D8: =_xlfn.XLOOKUP(B8,'Mitigation Map'!H:H,'Mitigation Map'!M:M, "") -> 0 | E8: =_xlfn.XLOOKUP(F8,'Mitigation Map'!O:O,'Mitigation Map'!N:N,"") | F8: =_xlfn.XLOOKUP(B8,'Mitigation Map'!H:H, 'Mitigation Map'!O:O, "No Mitigation Found") -> 0 | G8: =_xlfn.XLOOKUP(F8,'Mitigation Map'!O:O,'Mitigation Map'!P:P,"") | H8: =_xlfn.XLOOKUP(F8,'Mitigation Map'!O:O,'Mitigation Map'!Q:Q) -> #N/A | I8: =_xlfn.XLOOKUP(F8,'Mitigation Map'!O:O, 'Mitigation Map'!R:R, "") | J8: =IF(OR($J$3="", F8=""), "", $J$3) -> 45880 | K8: =IF(OR(J8="", _xlfn.XLOOKUP('Risk Treatment Plan'!F8, 'Mitigation Map'!O:O, 'Mitigation Map'!T:T, "")=""), "", J8 + _xlfn.XLOOKUP('Risk Treatment Plan'!F8, 'Mitigation Map'!O:O, 'Mitigation Map'!T:T)) | L8: =_xlfn.XLOOKUP(F8,'Mitigation Map'!O:O,'Mitigation Map'!U:U,"") | M8: =_xlfn.XLOOKUP(F8,'Mitigation Map'!O:O,'Mitigation Map'!V:V,"")
D9: =_xlfn.XLOOKUP(B9,'Mitigation Map'!H:H,'Mitigation Map'!M:M, "") -> 0 | E9: =_xlfn.XLOOKUP(F9,'Mitigation Map'!O:O,'Mitigation Map'!N:N,"") | F9: =_xlfn.XLOOKUP(B9,'Mitigation Map'!H:H, 'Mitigation Map'!O:O, "No Mitigation Found") -> 0 | G9: =_xlfn.XLOOKUP(F9,'Mitigation Map'!O:O,'Mitigation Map'!P:P,"") | H9: =_xlfn.XLOOKUP(F9,'Mitigation Map'!O:O,'Mitigation Map'!Q:Q) -> #N/A | I9: =_xlfn.XLOOKUP(F9,'Mitigation Map'!O:O, 'Mitigation Map'!R:R, "") | J9: =IF(OR($J$3="", F9=""), "", $J$3) -> 45880 | K9: =IF(OR(J9="", _xlfn.XLOOKUP('Risk Treatment Plan'!F9, 'Mitigation Map'!O:O, 'Mitigation Map'!T:T, "")=""), "", J9 + _xlfn.XLOOKUP('Risk Treatment Plan'!F9, 'Mitigation Map'!O:O, 'Mitigation Map'!T:T)) | L9: =_xlfn.XLOOKUP(F9,'Mitigation Map'!O:O,'Mitigation Map'!U:U,"") | M9: =_xlfn.XLOOKUP(F9,'Mitigation Map'!O:O,'Mitigation Map'!V:V,"")
D10: =_xlfn.XLOOKUP(B10,'Mitigation Map'!H:H,'Mitigation Map'!M:M, "") -> 0 | E10: =_xlfn.XLOOKUP(F10,'Mitigation Map'!O:O,'Mitigation Map'!N:N,"") | F10: =_xlfn.XLOOKUP(B10,'Mitigation Map'!H:H, 'Mitigation Map'!O:O, "No Mitigation Found") -> 0 | G10: =_xlfn.XLOOKUP(F10,'Mitigation Map'!O:O,'Mitigation Map'!P:P,"") | H10: =_xlfn.XLOOKUP(F10,'Mitigation Map'!O:O,'Mitigation Map'!Q:Q) -> #N/A | I10: =_xlfn.XLOOKUP(F10,'Mitigation Map'!O:O, 'Mitigation Map'!R:R, "") | J10: =IF(OR($J$3="", F10=""), "", $J$3) -> 45880 | K10: =IF(OR(J10="", _xlfn.XLOOKUP('Risk Treatment Plan'!F10, 'Mitigation Map'!O:O, 'Mitigation Map'!T:T, "")=""), "", J10 + _xlfn.XLOOKUP('Risk Treatment Plan'!F10, 'Mitigation Map'!O:O, 'Mitigation Map'!T:T)) | L10: =_xlfn.XLOOKUP(F10,'Mitigation Map'!O:O,'Mitigation Map'!U:U,"") | M10: =_xlfn.XLOOKUP(F10,'Mitigation Map'!O:O,'Mitigation Map'!V:V,"")
D11: =_xlfn.XLOOKUP(B11,'Mitigation Map'!H:H,'Mitigation Map'!M:M, "") -> 0 | E11: =_xlfn.XLOOKUP(F11,'Mitigation Map'!O:O,'Mitigation Map'!N:N,"") | F11: =_xlfn.XLOOKUP(B11,'Mitigation Map'!H:H, 'Mitigation Map'!O:O, "No Mitigation Found") -> 0 | G11: =_xlfn.XLOOKUP(F11,'Mitigation Map'!O:O,'Mitigation Map'!P:P,"") | H11: =_xlfn.XLOOKUP(F11,'Mitigation Map'!O:O,'Mitigation Map'!Q:Q) -> #N/A | I11: =_xlfn.XLOOKUP(F11,'Mitigation Map'!O:O, 'Mitigation Map'!R:R, "") | J11: =IF(OR($J$3="", F11=""), "", $J$3) -> 45880 | K11: =IF(OR(J11="", _xlfn.XLOOKUP('Risk Treatment Plan'!F11, 'Mitigation Map'!O:O, 'Mitigation Map'!T:T, "")=""), "", J11 + _xlfn.XLOOKUP('Risk Treatment Plan'!F11, 'Mitigation Map'!O:O, 'Mitigation Map'!T:T)) | L11: =_xlfn.XLOOKUP(F11,'Mitigation Map'!O:O,'Mitigation Map'!U:U,"") | M11: =_xlfn.XLOOKUP(F11,'Mitigation Map'!O:O,'Mitigation Map'!V:V,"")
D12: =_xlfn.XLOOKUP(B12,'Mitigation Map'!H:H,'Mitigation Map'!M:M, "") -> 0 | E12: =_xlfn.XLOOKUP(F12,'Mitigation Map'!O:O,'Mitigation Map'!N:N,"") | F12: =_xlfn.XLOOKUP(B12,'Mitigation Map'!H:H, 'Mitigation Map'!O:O, "No Mitigation Found") -> 0 | G12: =_xlfn.XLOOKUP(F12,'Mitigation Map'!O:O,'Mitigation Map'!P:P,"") | H12: =_xlfn.XLOOKUP(F12,'Mitigation Map'!O:O,'Mitigation Map'!Q:Q) -> #N/A | I12: =_xlfn.XLOOKUP(F12,'Mitigation Map'!O:O, 'Mitigation Map'!R:R, "") | J12: =IF(OR($J$3="", F12=""), "", $J$3) -> 45880 | K12: =IF(OR(J12="", _xlfn.XLOOKUP('Risk Treatment Plan'!F12, 'Mitigation Map'!O:O, 'Mitigation Map'!T:T, "")=""), "", J12 + _xlfn.XLOOKUP('Risk Treatment Plan'!F12, 'Mitigation Map'!O:O, 'Mitigation Map'!T:T)) | L12: =_xlfn.XLOOKUP(F12,'Mitigation Map'!O:O,'Mitigation Map'!U:U,"") | M12: =_xlfn.XLOOKUP(F12,'Mitigation Map'!O:O,'Mitigation Map'!V:V,"")
D13: =_xlfn.XLOOKUP(B13,'Mitigation Map'!H:H,'Mitigation Map'!M:M, "") -> 0 | E13: =_xlfn.XLOOKUP(F13,'Mitigation Map'!O:O,'Mitigation Map'!N:N,"") | F13: =_xlfn.XLOOKUP(B13,'Mitigation Map'!H:H, 'Mitigation Map'!O:O, "No Mitigation Found") -> 0 | G13: =_xlfn.XLOOKUP(F13,'Mitigation Map'!O:O,'Mitigation Map'!P:P,"") | H13: =_xlfn.XLOOKUP(F13,'Mitigation Map'!O:O,'Mitigation Map'!Q:Q) -> #N/A | I13: =_xlfn.XLOOKUP(F13,'Mitigation Map'!O:O, 'Mitigation Map'!R:R, "") | J13: =IF(OR($J$3="", F13=""), "", $J$3) -> 45880 | K13: =IF(OR(J13="", _xlfn.XLOOKUP('Risk Treatment Plan'!F13, 'Mitigation Map'!O:O, 'Mitigation Map'!T:T, "")=""), "", J13 + _xlfn.XLOOKUP('Risk Treatment Plan'!F13, 'Mitigation Map'!O:O, 'Mitigation Map'!T:T)) | L13: =_xlfn.XLOOKUP(F13,'Mitigation Map'!O:O,'Mitigation Map'!U:U,"") | M13: =_xlfn.XLOOKUP(F13,'Mitigation Map'!O:O,'Mitigation Map'!V:V,"")
D14: =_xlfn.XLOOKUP(B14,'Mitigation Map'!H:H,'Mitigation Map'!M:M, "") -> 0 | E14: =_xlfn.XLOOKUP(F14,'Mitigation Map'!O:O,'Mitigation Map'!N:N,"") | F14: =_xlfn.XLOOKUP(B14,'Mitigation Map'!H:H, 'Mitigation Map'!O:O, "No Mitigation Found") -> 0 | G14: =_xlfn.XLOOKUP(F14,'Mitigation Map'!O:O,'Mitigation Map'!P:P,"") | H14: =_xlfn.XLOOKUP(F14,'Mitigation Map'!O:O,'Mitigation Map'!Q:Q) -> #N/A | I14: =_xlfn.XLOOKUP(F14,'Mitigation Map'!O:O, 'Mitigation Map'!R:R, "") | J14: =IF(OR($J$3="", F14=""), "", $J$3) -> 45880 | K14: =IF(OR(J14="", _xlfn.XLOOKUP('Risk Treatment Plan'!F14, 'Mitigation Map'!O:O, 'Mitigation Map'!T:T, "")=""), "", J14 + _xlfn.XLOOKUP('Risk Treatment Plan'!F14, 'Mitigation Map'!O:O, 'Mitigation Map'!T:T)) | L14: =_xlfn.XLOOKUP(F14,'Mitigation Map'!O:O,'Mitigation Map'!U:U,"") | M14: =_xlfn.XLOOKUP(F14,'Mitigation Map'!O:O,'Mitigation Map'!V:V,"")
D15: =_xlfn.XLOOKUP(B15,'Mitigation Map'!H:H,'Mitigation Map'!M:M, "") -> 0 | E15: =_xlfn.XLOOKUP(F15,'Mitigation Map'!O:O,'Mitigation Map'!N:N,"") | F15: =_xlfn.XLOOKUP(B15,'Mitigation Map'!H:H, 'Mitigation Map'!O:O, "No Mitigation Found") -> 0 | G15: =_xlfn.XLOOKUP(F15,'Mitigation Map'!O:O,'Mitigation Map'!P:P,"") | H15: =_xlfn.XLOOKUP(F15,'Mitigation Map'!O:O,'Mitigation Map'!Q:Q) -> #N/A | I15: =_xlfn.XLOOKUP(F15,'Mitigation Map'!O:O, 'Mitigation Map'!R:R, "") | J15: =IF(OR($J$3="", F15=""), "", $J$3) -> 45880 | K15: =IF(OR(J15="", _xlfn.XLOOKUP('Risk Treatment Plan'!F15, 'Mitigation Map'!O:O, 'Mitigation Map'!T:T, "")=""), "", J15 + _xlfn.XLOOKUP('Risk Treatment Plan'!F15, 'Mitigation Map'!O:O, 'Mitigation Map'!T:T)) | L15: =_xlfn.XLOOKUP(F15,'Mitigation Map'!O:O,'Mitigation Map'!U:U,"") | M15: =_xlfn.XLOOKUP(F15,'Mitigation Map'!O:O,'Mitigation Map'!V:V,"")
... D46: =_xlfn.XLOOKUP(B46,'Mitigation Map'!H:H,'Mitigation Map'!M:M, "") -> 0 | E46: =_xlfn.XLOOKUP(F46,'Mitigation Map'!O:O,'Mitigation Map'!N:N,"") | F46: =_xlfn.XLOOKUP(B46,'Mitigation Map'!H:H, 'Mitigation Map'!O:O, "No Mitigation Found") -> 0 | G46: =_xlfn.XLOOKUP(F46,'Mitigation Map'!O:O,'Mitigation Map'!P:P,"") | H46: =_xlfn.XLOOKUP(F46,'Mitigation Map'!O:O,'Mitigation Map'!Q:Q) -> #N/A | I46: =_xlfn.XLOOKUP(F46,'Mitigation Map'!O:O, 'Mitigation Map'!R:R, "") | J46: =IF(OR($J$3="", F46=""), "", $J$3) -> 45880 | K46: =IF(OR(J46="", _xlfn.XLOOKUP('Risk Treatment Plan'!F46, 'Mitigation Map'!O:O, 'Mitigation Map'!T:T, "")=""), "", J46 + _xlfn.XLOOKUP('Risk Treatment Plan'!F46, 'Mitigation Map'!O:O, 'Mitigation Map'!T:T)) | L46: =_xlfn.XLOOKUP(F46,'Mitigation Map'!O:O,'Mitigation Map'!U:U,"") | M46: =_xlfn.XLOOKUP(F46,'Mitigation Map'!O:O,'Mitigation Map'!V:V,"")
J47: =IF($J$3="", "", $J$3) -> 45880 | K47: =IF(J47="", "", J47 + 7) -> 45887
J48: =IF($J$3="", "", $J$3) -> 45880 | K48: =IF(J48="", "", J48 + 7) -> 45887
J49: =IF($J$3="", "", $J$3) -> 45880 | K49: =IF(J49="", "", J49 + 7) -> 45887
J50: =IF($J$3="", "", $J$3) -> 45880 | K50: =IF(J50="", "", J50 + 7) -> 45887

Sheet Mitigation Map
B2: Note: The default risk rating is based on inherent risk, calculated using data subject impact and likelihood. This rating is not final and may change based on your assessment as the process or system owner. To request a change, consult your Data Protection Officer (DPO). If approved, the rating can be updated.
B5: Transparency
B6: No. | C6: Questions | F6: Yes/No/ N/A | G6: Response | H6: Threats/Vulnerabilities | I6: Risk | J6: Legal Basis | K6: Impact | L6: Probability | M6: Risk Rating | N6: Risk Treatment | O6: Mitigation Measure | P6: Status | Q6: Residual Risk Rating | R6: Control Reference | S6: Start Date | T6: Completion Date | U6: Review Frequency | V6: Risk Owner
B7: 1 | C7: 1. Are data subjects informed of the following details before or shortly after their personal data is collected (Privacy Notice)? Check all present | F7: ='P3 Gen Data Privacy Principles'!F7 -> 0 | H7: =IF(F7="No", "Absence of a comprehensive and timely privacy notice creates a transparency gap, weakening data subjects' ability to make informed decisions and exercise their rights.", "") | I7: =IF(F7="No", "Violation of general privacy principles – Transparency Violation of data subject rights - Rights to be informed", "") | J7: =IF(F7="No", "SEC. 11, DPA SEC. 16 (a) (b), DPA", "") | K7: =IF(AND(F7="No", 'P1 Threshold Analysis'!D5="Yes"), 4, IF(AND(F7="No", COUNTIF(F8:F17, "False")>9), 4, IF(AND(F7="No", COUNTIF(F8:F17, "True")>0), 3, ""))) | L7: =IF(AND(F7="No", 'P1 Threshold Analysis'!D5="Yes"), 4, IF(AND(F7="No", COUNTIF(F8:F17, "False")>9), 4, IF(AND(F7="No", COUNTIF(F8:F17, "True")>0), 3, ""))) | M7: =IF(OR(K7="", L7=""), "", IF(K7*L7>=10, IF(K7*L7<=16, "High Risk", ""), IF(K7*L7>=6, IF(K7*L7<=9, "Medium Risk", ""), IF(K7*L7>=2, IF(K7*L7<=4, "Low Risk", ""), IF(K7*L7=1, "Negligible", ""))))) | N7: Reduce | O7: Develop and implement a layered privacy notice in compliance with Section 3(A) of NPC Circular 2023-04, with the minimum required information presented up front. Use just-in-time notice at data collection point to provide context-specific, easily accessible information. Ensure the Full Privacy Notice satisfies Section 18(a) and Section 34(a)(2) of the DPA IRR and is linked or accessible from all layered and just-in-time notices. Establish procedures for periodic review and update of all notices. | P7: Planned | Q7: Low | R7: SECS. 18(a), 34 (a)(2), IRR SECS. 3(A) 9(C), NPC Circular 2023-04 | S7: [Reflect Calendar] | T7: 7 | U7: Annual or upon any significant change to data processing activities | V7: System/Process Owner
C8: a. Description of the personal data to be processed | F8: ='P3 Gen Data Privacy Principles'!F8 -> FALSE
C9: b. Purposes of processing, including direct marketing, profiling or historical, statistical or scientific purpose if applicable | F9: ='P3 Gen Data Privacy Principles'!F9 -> FALSE
C10: c. Basis of processing, when not based on consent | F10: ='P3 Gen Data Privacy Principles'!F10 -> FALSE
C11: d. Scope and method of processing | F11: ='P3 Gen Data Privacy Principles'!F11 -> FALSE
C12: e. Recipients or categories of recipients who may receive the personal data | F12: ='P3 Gen Data Privacy Principles'!F12 -> FALSE
C13: f. Methods used for automated access (cookie notification), if allowed by the data subject, including the extent of the authorization, the logic involved, and the significance and potential consequences of such processing | F13: ='P3 Gen Data Privacy Principles'!F13 -> FALSE | AZ13: Use of complex or technical language in privacy notices makes it difficult for data subjects to understand how their personal data is processed, increasing the risk of uninformed consent (if processing is based on consent) and non-compliance with transparency obligations.
C14: g. Risks and safeguards involved in the processing | F14: ='P3 Gen Data Privacy Principles'!F14 -> FALSE
C15: h. Identity and contact details of the PIC (your organization) or its representative (DPO) | F15: ='P3 Gen Data Privacy Principles'!F15 -> FALSE
C16: i. Retention period | F16: ='P3 Gen Data Privacy Principles'!F16 -> FALSE
C17: j. Data subject rights and the process for exercising them | F17: ='P3 Gen Data Privacy Principles'!F17 -> FALSE
B18: 2 | C18: Is information and communication about personal data processing easy to access and understand, using clear and plain language (Privacy Notice)? | F18: ='P3 Gen Data Privacy Principles'!F18 -> 0 | H18: =IF(F18="No", "Use of complex or technical language in privacy notices makes it difficult for data subjects to understand how their personal data is processed, increasing the risk of uninformed consent and non-compliance with transparency obligations.", "") | I18: =IF(F18="No","Violation of general privacy principles – Transparency", "") | J18: =IF(F18="No","SEC. 11, DPA ", "") | K18: =IF(AND(F7="No", COUNTIF(F8:F17, "False")>9), 4, IF(AND(F18="No", 'P1 Threshold Analysis'!D5="Yes"), 3, IF(AND(F18="No", COUNTIF(F8:F17, "FALSE")>0, 'P1 Threshold Analysis'!D4="Yes", 'P1 Threshold Analysis'!D5="No"), 2, ""))) | L18: =IF(AND(F7="No", COUNTIF(F8:F17, "False")>9), 4, IF(AND(F18="No", 'P1 Threshold Analysis'!D5="Yes"), 3, IF(AND(F18="No", COUNTIF(F8:F17, "FALSE")>0, 'P1 Threshold Analysis'!D4="Yes", 'P1 Threshold Analysis'!D5="No"), 2, ""))) | M18: =IF(OR(K18="", L18=""), "", IF(K18*L18>=10, IF(K18*L18<=16, "High Risk", ""), IF(K18*L18>=6, IF(K18*L18<=9, "Medium Risk", ""), IF(K18*L18>=2, IF(K18*L18<=4, "Low Risk", ""), IF(K18*L18=1, "Negligible", ""))))) | N18: Reduce | O18: Develop a privacy notice using clear and plain language. Ensure that the information is easy to access, understandable, and readily available in a format and language or dialect that is appropriate for the target audience. Validate comprehension through testing with representative users. | P18: Planned | Q18: Low | R18: SEC. 18(a), IRR SEC. 3(E), NPC Circular 2023-04 | T18: 7 | U18: Annual or upon any significant change to data processing activities | V18: System/Process Owner
B19: Legitimate Purpose / Lawfulness
B20: 1 | C20: Is the processing of personal data compatible with a declared and specified purpose which are not contrary to law, morals, or public policy? | F20: ='P3 Gen Data Privacy Principles'!F20 -> 0 | H20: =IF(F20="No", "Processing personal data for purposes that are incompatible with the declared purpose and contrary to law, morals, or public policy may lead to regulatory sanctions, reputational damage, and loss of public trust.", "") | I20: =IF(F20="No", "Violation of general privacy principles – Legitimate Purpose", "") | J20: =IF(F20="No", " SEC. 11, DPA", "") | K20: =IF(AND(F20="No", 'P1 Threshold Analysis'!D5="Yes"),4, IF(AND(F20="No", 'P1 Threshold Analysis'!D4="Yes"), 3,"")) | L20: =IF(AND(F20="No", 'P1 Threshold Analysis'!D5="Yes"),4, IF(AND(F20="No", 'P1 Threshold Analysis'!D4="Yes"), 3,"")) | M20: =IF(OR(K20="", L20=""), "", IF(K20*L20>=10, IF(K20*L20<=16, "High Risk", ""), IF(K20*L20>=6, IF(K20*L20<=9, "Medium Risk", ""), IF(K20*L20>=2, IF(K20*L20<=4, "Low Risk", ""), IF(K20*L20=1, "Negligible", ""))))) | N20: Reduce | O20: Establish a Purpose Declaration and Compatibility Framework requiring that all personal data processing activities declare a specific, lawful, and clearly defined purpose prior to collection, ensuring it is not contrary to law, morals, good customs, public order, or public policy. For any new or secondary data use, conduct a Purpose Compatibility Assessment using the following criteria and guiding questions: Is the new purpose closely related to the originally declared purpose? Would a data subject reasonably expect this new use given the context of collection? Does the new purpose involve sensitive personal data or increase risk? Could this use cause harm, confusion, or distress? Are there sufficient safeguards (e.g., anonymization, opt-out) to mitigate risks? All purposes must be documented in the Data Mapping, reflected in layered privacy notices, and define the boundaries of data subject consent. | P20: Planned | Q20: Low | R20: SEC. 18(b), IRR SEC. 4, NPC Circular 2023-04 | T20: 1 | U20: Annual or upon any significant change to data processing activities | V20: System/Process Owner
B21: 2 | C21: Is the processing based on Section 4 (for special cases), Section 12 (for personal information), or Section 13 (for sensitive and privileged information) of the DPA? | F21: ='P3 Gen Data Privacy Principles'!F21 -> 0 | H21: =IF(F21="No", "Processing personal data without a valid legal basis under Sections 4, 12, or 13 of the Data Privacy Act exposes the organization to legal liabilities, and penalties.", "") | I21: =IF(F21="No", "Violation of general privacy principles – Legitimate Purpose", "") | J21: =IF(F21="No", " SEC. 11, DPA", "") | K21: =IF(AND(F21="No", 'P1 Threshold Analysis'!D5="Yes"),4, IF(AND(F21="No", 'P1 Threshold Analysis'!D4="Yes"), 3,"")) | L21: =IF(AND(F21="No", 'P1 Threshold Analysis'!D5="Yes"),4, IF(AND(F21="No", 'P1 Threshold Analysis'!D4="Yes"), 3,"")) | M21: =IF(OR(K21="", L21=""), "", IF(K21*L21>=10, IF(K21*L21<=16, "High Risk", ""), IF(K21*L21>=6, IF(K21*L21<=9, "Medium Risk", ""), IF(K21*L21>=2, IF(K21*L21<=4, "Low Risk", ""), IF(K21*L21=1, "Negligible", ""))))) | N21: Reduce | O21: Ensure that all processing activities are mapped to one of the lawful bases (e.g., consent, contract, legal obligation). Integrate checks during the PIA processes. Train key departments on identifying and applying appropriate legal bases. | P21: Planned | Q21: Low | R21: SECS. 4, 12, 13, DPA | T21: 1 | U21: Annual or upon any significant change to data processing activities | V21: System/Process Owner
B22: Proportionality / Data minimization
B23: Personal Data | D23: Adequate (enough to fulfil the purpose) | E23: Relevant & Suitable (related & appropriate) | F23: Necessary | G23: Remarks | H23: Threats/Vulnerabilities | I23: Risk | J23: Legal Basis | K23: Impact | L23: Probability | M23: Risk Rating
B24: ='P3 Gen Data Privacy Principles'!B24 -> Name, Age | D24: ='P3 Gen Data Privacy Principles'!D24 -> No | E24: ='P3 Gen Data Privacy Principles'!E24 -> No | F24: ='P3 Gen Data Privacy Principles'!F24 -> Required | G24: ='P3 Gen Data Privacy Principles'!G24 -> 0 | H24: =IF(OR(D24="No", E24="No", F24="No", F24="Optional"), "Collecting excessive or irrelevant personal data increases the risk of data misuse, breaches, and non-compliance with proportionality/data minimization principles.", "") -> Collecting excessive or irrelevant personal data increases the risk of data misuse, breaches, and non-compliance with proportionality/data minimization principles. | I24: =IF(OR(D24="No", E24="No", F24="No", F24="Optional"), "Violation of general privacy principles – Proportionality / Data Minimization", "") -> Violation of general privacy principles – Proportionality / Data Minimization | J24: =IF(OR(D24="No", E24="No", F24="Optional"), "SEC. 11, DPA ", "") -> SEC. 11, DPA | K24: =IF(AND('P1 Threshold Analysis'!D5="Yes", OR(D24="No", E24="No", F24="No", F24="Optional")), 4, IF(AND('P1 Threshold Analysis'!D4="Yes", OR(D24="No", E24="No", F24="No", F24="Optional")), 3, "")) | L24: =IF(AND('P1 Threshold Analysis'!D5="Yes", OR(D24="No", E24="No", F24="No", F24="Optional")), 4, IF(AND('P1 Threshold Analysis'!D4="Yes", OR(D24="No", E24="No", F24="No", F24="Optional")), 3, "")) | M24: =IF(OR(K24="", L24=""), "", IF(K24*L24>=10, IF(K24*L24<=16, "High Risk", ""), IF(K24*L24>=6, IF(K24*L24<=9, "Medium Risk", ""), IF(K24*L24>=2, IF(K24*L24<=4, "Low Risk", ""), IF(K24*L24=1, "Negligible", ""))))) | N24: Reduce | O24: For Collection Form - Conduct regular Data Mapping review to ensure only necessary personal data is collected for each processing activity. Implement field-level data minimization controls in systems. Include proportionality checks in PIA. Train process owners and data handlers on the data minimization principle. For Off-the-Shelf Software - The organization shall adopt Privacy-By-Design and Privacy-By-Default principles in the use and configuration of off-the-shelf software, tools, or systems. A Privacy Impact Assessment (PIA) shall be conducted prior to the use or deployment of such systems to evaluate their alignment with data protection requirements. Any system functions or features that lack a lawful basis or are inconsistent with general data privacy principles must be switched off, deactivated, or appropriately configured. Privacy requirements shall be embedded at every stage of system design and implementation (privacy engineering), and only those functionalities necessary and proportionate to the legitimate purpose of the processing shall be enabled by default. | P24: Planned | Q24: Low | R24: For Colection Form SEC. 11(d), DPA For Off-the-Shelf Software SEC. 11(d), DPA SECS. 7, 8, 9, NPC Circular 2023-06 | T24: 14 | U24: Annual or upon any significant change to data processing activities | V24: System/Process Owner
B25: ='P3 Gen Data Privacy Principles'!B25 -> 0 | D25: ='P3 Gen Data Privacy Principles'!D25 -> 0 | E25: ='P3 Gen Data Privacy Principles'!E25 -> 0 | F25: ='P3 Gen Data Privacy Principles'!F25 -> 0 | G25: ='P3 Gen Data Privacy Principles'!G25 -> 0 | H25: =IF(OR(D25="No", E25="No", F25="No", F25="Optional"), "Collecting excessive or irrelevant personal data increases the risk of data misuse, breaches, and non-compliance with proportionality/data minimization principles.", "") | I25: =IF(OR(D25="No", E25="No", F25="No", F25="Optional"), "Violation of general privacy principles – Proportionality / Data Minimization", "") | J25: =IF(OR(D25="No", E25="No", F25="No", F25="Optional"), "SEC. 11, DPA ", "") | K25: =IF(AND('P1 Threshold Analysis'!D5="Yes", OR(D25="No", E25="No", F25="No", F25="Optional")), 4, IF(AND('P1 Threshold Analysis'!D4="Yes", OR(D25="No", E25="No", F25="No", F25="Optional")), 3, "")) | L25: =IF(AND('P1 Threshold Analysis'!D5="Yes", OR(D25="No", E25="No", F25="No", F25="Optional")), 4, IF(AND('P1 Threshold Analysis'!D4="Yes", OR(D25="No", E25="No", F25="No", F25="Optional")), 3, "")) | M25: =IF(OR(K25="", L25=""), "", IF(K25*L25>=10, IF(K25*L25<=16, "High Risk", ""), IF(K25*L25>=6, IF(K25*L25<=9, "Medium Risk", ""), IF(K25*L25>=2, IF(K25*L25<=4, "Low Risk", ""), IF(K25*L25=1, "Negligible", ""))))) | N25: Reduce | O25: For Collection Form - Conduct regular Data Mapping review to ensure only necessary personal data is collected for each processing activity. Implement field-level data minimization controls in systems. Include proportionality checks in PIA. Train process owners and data handlers on the data minimization principle. For Off-the-Shelf Software - The organization shall adopt Privacy-By-Design and Privacy-By-Default principles in the use and configuration of off-the-shelf software, tools, or systems. A Privacy Impact Assessment (PIA) shall be conducted prior to the use or deployment of such systems to evaluate their alignment with data protection requirements. Any system functions or features that lack a lawful basis or are inconsistent with general data privacy principles must be switched off, deactivated, or appropriately configured. Privacy requirements shall be embedded at every stage of system design and implementation (privacy engineering), and only those functionalities necessary and proportionate to the legitimate purpose of the processing shall be enabled by default. | P25: Planned | Q25: Low | R25: For Colection Form SEC. 11(d), DPA For Off-the-Shelf Software SEC. 11(d), DPA SECS. 7, 8, 9, NPC Circular 2023-07 | T25: 14 | U25: Annual or upon any significant change to data processing activities | V25: System/Process Owner
B26: ='P3 Gen Data Privacy Principles'!B26 -> 0 | D26: ='P3 Gen Data Privacy Principles'!D26 -> 0 | E26: ='P3 Gen Data Privacy Principles'!E26 -> 0 | F26: ='P3 Gen Data Privacy Principles'!F26 -> 0 | G26: ='P3 Gen Data Privacy Principles'!G26 -> 0 | H26: =IF(OR(D26="No", E26="No", F26="No", F26="Optional"), "Collecting excessive or irrelevant personal data increases the risk of data misuse, breaches, and non-compliance with proportionality/data minimization principles.", "") | I26: =IF(OR(D26="No", E26="No", F26="No", F26="Optional"), "Violation of general privacy principles – Proportionality / Data Minimization", "") | J26: =IF(OR(D26="No", E26="No", F26="No", F26="Optional"), "SEC. 11, DPA ", "") | K26: =IF(AND('P1 Threshold Analysis'!D5="Yes", OR(D26="No", E26="No", F26="No", F26="Optional")), 4, IF(AND('P1 Threshold Analysis'!D4="Yes", OR(D26="No", E26="No", F26="No", F26="Optional")), 3, "")) | L26: =IF(AND('P1 Threshold Analysis'!D5="Yes", OR(D26="No", E26="No", F26="No", F26="Optional")), 4, IF(AND('P1 Threshold Analysis'!D4="Yes", OR(D26="No", E26="No", F26="No", F26="Optional")), 3, "")) | M26: =IF(OR(K26="", L26=""), "", IF(K26*L26>=10, IF(K26*L26<=16, "High Risk", ""), IF(K26*L26>=6, IF(K26*L26<=9, "Medium Risk", ""), IF(K26*L26>=2, IF(K26*L26<=4, "Low Risk", ""), IF(K26*L26=1, "Negligible", ""))))) | N26: Reduce | O26: For Collection Form - Conduct regular Data Mapping review to ensure only necessary personal data is collected for each processing activity. Implement field-level data minimization controls in systems. Include proportionality checks in PIA. Train process owners and data handlers on the data minimization principle. For Off-the-Shelf Software - The organization shall adopt Privacy-By-Design and Privacy-By-Default principles in the use and configuration of off-the-shelf software, tools, or systems. A Privacy Impact Assessment (PIA) shall be conducted prior to the use or deployment of such systems to evaluate their alignment with data protection requirements. Any system functions or features that lack a lawful basis or are inconsistent with general data privacy principles must be switched off, deactivated, or appropriately configured. Privacy requirements shall be embedded at every stage of system design and implementation (privacy engineering), and only those functionalities necessary and proportionate to the legitimate purpose of the processing shall be enabled by default. | P26: Planned | Q26: Low | R26: For Colection Form SEC. 11(d), DPA For Off-the-Shelf Software SEC. 11(d), DPA SECS. 7, 8, 9, NPC Circular 2023-08 | T26: 14 | U26: Annual or upon any significant change to data processing activities | V26: System/Process Owner
B27: ='P3 Gen Data Privacy Principles'!B27 -> 0 | D27: ='P3 Gen Data Privacy Principles'!D27 -> 0 | E27: ='P3 Gen Data Privacy Principles'!E27 -> 0 | F27: ='P3 Gen Data Privacy Principles'!F27 -> 0 | G27: ='P3 Gen Data Privacy Principles'!G27 -> 0 | H27: =IF(OR(D27="No", E27="No", F27="No", F27="Optional"), "Collecting excessive or irrelevant personal data increases the risk of data misuse, breaches, and non-compliance with proportionality/data minimization principles.", "") | I27: =IF(OR(D27="No", E27="No", F27="No", F27="Optional"), "Violation of general privacy principles – Proportionality / Data Minimization", "") | J27: =IF(OR(D27="No", E27="No", F27="No", F27="Optional"), "SEC. 11, DPA ", "") | K27: =IF(AND('P1 Threshold Analysis'!D5="Yes", OR(D27="No", E27="No", F27="No", F27="Optional")), 4, IF(AND('P1 Threshold Analysis'!D4="Yes", OR(D27="No", E27="No", F27="No", F27="Optional")), 3, "")) | L27: =IF(AND('P1 Threshold Analysis'!D5="Yes", OR(D27="No", E27="No", F27="No", F27="Optional")), 4, IF(AND('P1 Threshold Analysis'!D4="Yes", OR(D27="No", E27="No", F27="No", F27="Optional")), 3, "")) | M27: =IF(OR(K27="", L27=""), "", IF(K27*L27>=10, IF(K27*L27<=16, "High Risk", ""), IF(K27*L27>=6, IF(K27*L27<=9, "Medium Risk", ""), IF(K27*L27>=2, IF(K27*L27<=4, "Low Risk", ""), IF(K27*L27=1, "Negligible", ""))))) | N27: Reduce | O27: For Collection Form - Conduct regular Data Mapping review to ensure only necessary personal data is collected for each processing activity. Implement field-level data minimization controls in systems. Include proportionality checks in PIA. Train process owners and data handlers on the data minimization principle. For Off-the-Shelf Software - The organization shall adopt Privacy-By-Design and Privacy-By-Default principles in the use and configuration of off-the-shelf software, tools, or systems. A Privacy Impact Assessment (PIA) shall be conducted prior to the use or deployment of such systems to evaluate their alignment with data protection requirements. Any system functions or features that lack a lawful basis or are inconsistent with general data privacy principles must be switched off, deactivated, or appropriately configured. Privacy requirements shall be embedded at every stage of system design and implementation (privacy engineering), and only those functionalities necessary and proportionate to the legitimate purpose of the processing shall be enabled by default. | P27: Planned | Q27: Low | R27: For Colection Form SEC. 11(d), DPA For Off-the-Shelf Software SEC. 11(d), DPA SECS. 7, 8, 9, NPC Circular 2023-09 | T27: 14 | U27: Annual or upon any significant change to data processing activities | V27: System/Process Owner
B28: ='P3 Gen Data Privacy Principles'!B28 -> 0 | D28: ='P3 Gen Data Privacy Principles'!D28 -> 0 | E28: ='P3 Gen Data Privacy Principles'!E28 -> 0 | F28: ='P3 Gen Data Privacy Principles'!F28 -> 0 | G28: ='P3 Gen Data Privacy Principles'!G28 -> 0 | H28: =IF(OR(D28="No", E28="No", F28="No", F28="Optional"), "Collecting excessive or irrelevant personal data increases the risk of data misuse, breaches, and non-compliance with proportionality/data minimization principles.", "") | I28: =IF(OR(D28="No", E28="No", F28="No", F28="Optional"), "Violation of general privacy principles – Proportionality / Data Minimization", "") | J28: =IF(OR(D28="No", E28="No", F28="No", F28="Optional"), "SEC. 11, DPA ", "") | K28: =IF(AND('P1 Threshold Analysis'!D5="Yes", OR(D28="No", E28="No", F28="No", F28="Optional")), 4, IF(AND('P1 Threshold Analysis'!D4="Yes", OR(D28="No", E28="No", F28="No", F28="Optional")), 3, "")) | L28: =IF(AND('P1 Threshold Analysis'!D5="Yes", OR(D28="No", E28="No", F28="No", F28="Optional")), 4, IF(AND('P1 Threshold Analysis'!D4="Yes", OR(D28="No", E28="No", F28="No", F28="Optional")), 3, "")) | M28: =IF(OR(K28="", L28=""), "", IF(K28*L28>=10, IF(K28*L28<=16, "High Risk", ""), IF(K28*L28>=6, IF(K28*L28<=9, "Medium Risk", ""), IF(K28*L28>=2, IF(K28*L28<=4, "Low Risk", ""), IF(K28*L28=1, "Negligible", ""))))) | N28: Reduce | O28: For Collection Form - Conduct regular Data Mapping review to ensure only necessary personal data is collected for each processing activity. Implement field-level data minimization controls in systems. Include proportionality checks in PIA. Train process owners and data handlers on the data minimization principle. For Off-the-Shelf Software - The organization shall adopt Privacy-By-Design and Privacy-By-Default principles in the use and configuration of off-the-shelf software, tools, or systems. A Privacy Impact Assessment (PIA) shall be conducted prior to the use or deployment of such systems to evaluate their alignment with data protection requirements. Any system functions or features that lack a lawful basis or are inconsistent with general data privacy principles must be switched off, deactivated, or appropriately configured. Privacy requirements shall be embedded at every stage of system design and implementation (privacy engineering), and only those functionalities necessary and proportionate to the legitimate purpose of the processing shall be enabled by default. | P28: Planned | Q28: Low | R28: For Colection Form SEC. 11(d), DPA For Off-the-Shelf Software SEC. 11(d), DPA SECS. 7, 8, 9, NPC Circular 2023-10 | T28: 14 | U28: Annual or upon any significant change to data processing activities | V28: System/Process Owner
B29: Fairness
B30: 1 | C30: Is the Privacy Notice / Consent Form presented objectively and neutrally, without deceptive or manipulative language or design? | F30: ='P3 Gen Data Privacy Principles'!F30 -> 0 | H30: =IF(F30="No", "The use of biased or manipulative language in the Privacy Notice/Consent Form undermines the clarity of consent, potentially leading to invalid consent and non-compliance with data protection regulations. ", "") | I30: =IF(F30="No", "Violation of general privacy principles – Fairness ", "") | J30: =IF(F30="No", "SEC. 11, DPA ", "") | K30: =IF(AND(F30="No", 'P1 Threshold Analysis'!D5="Yes"), 4, IF(AND(F30="No", 'P1 Threshold Analysis'!D4="Yes"),3,"")) | L30: =IF(AND(F30="No", 'P1 Threshold Analysis'!D5="Yes"), 4, IF(AND(F30="No", 'P1 Threshold Analysis'!D4="Yes"),3,"")) | M30: =IF(OR(K30="", L30=""), "", IF(K30*L30>=10, IF(K30*L30<=16, "High Risk", ""), IF(K30*L30>=6, IF(K30*L30<=9, "Medium Risk", ""), IF(K30*L30>=2, IF(K30*L30<=4, "Low Risk", ""), IF(K30*L30=1, "Negligible", ""))))) | N30: Reduce | O30: Ensure that all privacy notices and consent forms are written in clear, plain, and neutral language, making them easy to understand and access. Personal data shall be processed fairly and lawfully, without manipulation or undue pressure. Conduct fairness reviews to eliminate biased or coercive language. Integrate these checks into the Privacy Notice/Consent Development Protocol and validate with target audience testing or expert review. | P30: Planned | Q30: Low | R30: SEC. 19(b), IRR SECS. 6, 7, NPC Circular 2023-04 | T30: 7 | U30: Annual or upon any significant change to data processing activities | V30: System/Process Owner
B31: Data Quality / Accuracy
B32: 1 | C32: Is personal data accurate, and kept up to date? Check all present | F32: ='P3 Gen Data Privacy Principles'!F32 -> 0 | H32: =IF(F32="No", "Inaccurate or outdated personal data can lead to incorrect decisions, harm to data subjects, and non-compliance with data accuracy requirements, undermining the integrity of the processing system. ", "") | I32: =IF(F32="No", "Violation of general privacy principles – Accuracy ", "") | J32: =IF(F32="No", "SEC. 11, DPA ", "") | K32: =IF(AND(F32="No", 'P1 Threshold Analysis'!D5="Yes"), 4, IF(AND(F32="No", 'P1 Threshold Analysis'!D4="Yes"),3,"")) | L32: =IF(AND(F32="No", 'P1 Threshold Analysis'!D5="Yes"), 4, IF(AND(F32="No", 'P1 Threshold Analysis'!D4="Yes"),3,"")) | M32: =IF(OR(K32="", L32=""), "", IF(K32*L32>=10, IF(K32*L32<=16, "High Risk", ""), IF(K32*L32>=6, IF(K32*L32<=9, "Medium Risk", ""), IF(K32*L32>=2, IF(K32*L32<=4, "Low Risk", ""), IF(K32*L32=1, "Negligible", ""))))) | N32: Reduce | O32: Ensure that personal data is accurate and, where necessary for declared, specified, and legitimate purposes, kept up to date. Implement validation checks, periodic reviews, and self-service options for updates. Integrate accuracy requirements in data collection and processing workflows. | P32: Planned | Q32: Low | R32: SEC. 19(c)(1), IRR | T32: 30 | U32: Annual or upon any significant change to data processing activities | V32: System/Process Owner
C33: a. Verify data at collection | F33: ='P3 Gen Data Privacy Principles'!F33 -> FALSE
C34: b. Review and update personal data regularly | F34: ='P3 Gen Data Privacy Principles'!F34 -> FALSE
C35: c. Allow users to update their personal data securely | F35: ='P3 Gen Data Privacy Principles'!F35 -> FALSE
C36: d. Use reliable sources when updating records | F36: ='P3 Gen Data Privacy Principles'!F36 -> FALSE
B37: 2 | C37: Is inaccurate or incomplete data rectified, supplemented, destroyed or their further processing restricted? Check all present | F37: ='P3 Gen Data Privacy Principles'!F37 -> 0 | H37: =IF(F37="No", "Failure to rectify or restrict processing of inaccurate or incomplete data compromises data quality and may result in violations of data subjects’ rights. ", "") | I37: =IF(F37="No", "Violation of general privacy principles – Accuracy ", "") | J37: =IF(F37="No", "SEC. 11, DPA ", "") | K37: =IF(AND(F37="No", 'P1 Threshold Analysis'!D5="Yes"), 4, IF(AND(F37="No", 'P1 Threshold Analysis'!D4="Yes"),3,"")) | L37: =IF(AND(F37="No", 'P1 Threshold Analysis'!D5="Yes"), 4, IF(AND(F37="No", 'P1 Threshold Analysis'!D4="Yes"),3,"")) | M37: =IF(OR(K37="", L37=""), "", IF(K37*L37>=10, IF(K37*L37<=16, "High Risk", ""), IF(K37*L37>=6, IF(K37*L37<=9, "Medium Risk", ""), IF(K37*L37>=2, IF(K37*L37<=4, "Low Risk", ""), IF(K37*L37=1, "Negligible", ""))))) | N37: Reduce | O37: Implement measures to identify and correct inaccurate or incomplete data. Where applicable, such data must be rectified, supplemented, destroyed, or their further processing restricted. Integrate this requirement into data collection, system updates, and data subject rights procedures. Enable data subjects to request corrections and establish review checkpoints across the data lifecycle. | P37: Planned | Q37: Low | R37: SEC. 19(c)(2), IRR | T37: 30 | U37: Annual or upon any significant change to data processing activities | V37: System/Process Owner
C38: a. People can request corrections and erasure easily | F38: ='P3 Gen Data Privacy Principles'!F38 -> FALSE
C39: b. Data processing restrictions of inaccurate or complete data until rectified | F39: ='P3 Gen Data Privacy Principles'!F39 -> FALSE
C40: c. Secure disposal methods | F40: ='P3 Gen Data Privacy Principles'!F40 -> FALSE
B41: Purpose limitation
B42: 1 | C42: Is personal data collected for specified purpose not further processed in a manner that is incompatible with that purpose? Note: may be further processed for historical, statistical, or scientific purposes, and stored longer as allowed by law, provided appropriate security measures safeguard the data subject’s rights and freedoms. | F42: ='P3 Gen Data Privacy Principles'!F42 -> 0 | H42: =IF(F42="No", "Processing personal data for unspecified or incompatible purposes increases the risk of unauthorized use, undermining data subject trust and exposing the organization to regulatory penalties. ", "") | I42: =IF(F42="No", "Violation of general privacy principles – Purpose Limitation Unlawful Processing - Processing of Personal Data for Unauthorized Purposes ", "") | J42: =IF(F42="No", "SEC. 11, DPA SEC. 28, DPA ", "") | K42: =IF(AND(F42="No", 'P1 Threshold Analysis'!D5="Yes"), 4, IF(AND(F42="No", 'P1 Threshold Analysis'!D4="Yes"),3,"")) | L42: =IF(AND(F42="No", 'P1 Threshold Analysis'!D5="Yes"), 4, IF(AND(F42="No", 'P1 Threshold Analysis'!D4="Yes"),3,"")) | M42: =IF(OR(K42="", L42=""), "", IF(K42*L42>=10, IF(K42*L42<=16, "High Risk", ""), IF(K42*L42>=6, IF(K42*L42<=9, "Medium Risk", ""), IF(K42*L42>=2, IF(K42*L42<=4, "Low Risk", ""), IF(K42*L42=1, "Negligible", ""))))) | N42: Reduce | O42: Ensure that personal data is collected for a specified and declared purpose, and not further processed in a manner incompatible with that purpose. Require purpose documentation in Data Mapping and privacy notices. Conduct purpose compatibility assessments for secondary uses. Train staff to validate alignment before initiating processing activities. | P42: Planned | Q42: Low | R42: SEC. 19(a)(e), IRR | T42: 1 | U42: Annual or upon any significant change to data processing activities | V42: System/Process Owner
B43: Storage Limitation
B44: 1 | C44: Is personal data retained only for as long as necessary? Check all applicable | F44: ='P3 Gen Data Privacy Principles'!F44 -> 0 | H44: =IF(F44="No", "Retaining personal data longer than necessary increases the risk of data breaches, unauthorized access, and non-compliance with data retention policies.", "") | I44: =IF(F44="No", "Violation of general privacy principles – Storage Limitation","") | J44: =IF(F44="No", " SEC. 11, DPA ","") | K44: =IF(AND(F44="No", 'P1 Threshold Analysis'!D5="Yes"), 4, IF(AND(F44="No", 'P1 Threshold Analysis'!D4="Yes"),3,"")) | L44: =IF(AND(F44="No", 'P1 Threshold Analysis'!D5="Yes"), 4, IF(AND(F44="No", 'P1 Threshold Analysis'!D4="Yes"),3,"")) | M44: =IF(OR(K44="", L44=""), "", IF(K44*L44>=10, IF(K44*L44<=16, "High Risk", ""), IF(K44*L44>=6, IF(K44*L44<=9, "Medium Risk", ""), IF(K44*L44>=2, IF(K44*L44<=4, "Low Risk", ""), IF(K44*L44=1, "Negligible", ""))))) | N44: Reduce | O44: Store personal data only for as long as necessary for the specific, declared purpose for which it was initially processed. Establish and implement a documented Retention Policy that defines appropriate retention periods. Review and update the policy periodically, and ensure that data subjects are informed of the policy and any changes to it. Integrate retention controls in systems and disposal procedures. | P44: Planned | Q44: Low | R44: SEC. 19(d), IRR SEC. 9, NPC Circular 2023-06 | T44: 30 | U44: Annual or upon any significant change to data processing activities | V44: System/Process Owner
C45: a. To fulfill the declared, specified, and legitimate purpose | F45: ='P3 Gen Data Privacy Principles'!F45 -> FALSE
C46: b. For the establishment, exercise or defense of legal claims; or | F46: ='P3 Gen Data Privacy Principles'!F46 -> FALSE
C47: c. For legitimate business purposes aligned with industry standards | F47: ='P3 Gen Data Privacy Principles'!F47 -> FALSE
C48: d. Retention is allowed/required by law/appropriate government agency | F48: ='P3 Gen Data Privacy Principles'!F48 -> FALSE
C49: e. Aggregated (statistics, average, total numbers) or anonymized personal data may be kept beyond the necessary period. | F49: ='P3 Gen Data Privacy Principles'!F49 -> FALSE
B50: Rights to be informed (Included under the Transparency Principle)
A51: No. | B51: Questions | E51: Yes/No/N/A | G51: Response | H51: Threats/Vulnerabilities | I51: Risk | J51: Legal Basis | K51: Impact | L51: Probability | M51: Risk Rating | N51: Risk Treatment | O51: Mitigation Measure | P51: Status | Q51: Residual Risk Rating | R51: Control Reference | S51: Start Date | T51: Completion Date | U51: Review Frequency | V51: Risk Owner
A52: 1 | B52: (For consent) Do you obtain the data subject’s consent, evidenced by written, electronic, or recorded means, before processing their personal data? | E52: No | G52: ='P3 Data Subject Rights'!H11 -> 0 | H52: ='P3 Data Subject Rights'!I11 | I52: ='P3 Data Subject Rights'!J11 | J52: ='P3 Data Subject Rights'!K11 | K52: ='P3 Data Subject Rights'!L11 | L52: ='P3 Data Subject Rights'!M11 | M52: ='P3 Data Subject Rights'!N11 | N52: Reduce | O52: Obtain consent prior to collection or processing and ensure it is freely given, specific, informed, and evidenced through written, electronic, or recorded means. Consent must be time-bound to the declared, specified, and legitimate purpose, and must include a clear proposal from the PIC requesting authorization under stated terms (e.g., we request your consent, or by signing, you consent to the processing, etc.). Maintain verifiable records of consent and regularly review consent capture processes for compliance. | P52: Planned | Q52: Low | R52: SEC. 19(a)(1), IRR SECS. 3(D)(4), 11 NPC Circular 2023-04 | T52: 7 | U52: Annual or upon any significant change to data processing activities | V52: System/Process Owner
A53: 2 | B53: (For consent) Before obtaining consent, do you provide the following information clearly and concisely in the consent form or Privacy Notice? Check all present | E53: Yes | G53: ='P3 Data Subject Rights'!H12 -> 0 | H53: ='P3 Data Subject Rights'!I12 | I53: ='P3 Data Subject Rights'!J12 | J53: ='P3 Data Subject Rights'!K12 | K53: ='P3 Data Subject Rights'!L12 | L53: ='P3 Data Subject Rights'!M12 | M53: ='P3 Data Subject Rights'!N12 | N53: Reduce | O53: Ensure that all consent forms and privacy notices clearly inform the data subject of the nature, purpose, and extent of processing, including associated risks, safeguards, the identity of the PIC, the rights of the data subject, and how these rights may be exercised. At a minimum, include the information in Section 3(A), NPC Circular 2023-04. Present the information using layered notices, clear language, and accessible formats. Regularly review and update notices to ensure accuracy and compliance. | P53: Planned | Q53: Low | R53: SEC. 3(A), NPC Circular 2023-04 | T53: 7 | U53: Annual or upon any significant change to data processing activities | V53: System/Process Owner
B54: a. Description of the personal data to be processed | E54: Yes | G54: ='P3 Data Subject Rights'!H13 -> 0 | H54: ='P3 Data Subject Rights'!I13 -> 0 | I54: ='P3 Data Subject Rights'!J13 -> 0 | J54: ='P3 Data Subject Rights'!K13 -> 0 | K54: ='P3 Data Subject Rights'!L13 -> 0 | L54: ='P3 Data Subject Rights'!M13 -> 0 | M54: ='P3 Data Subject Rights'!N13 -> 0
B55: b. Purpose, nature, extent, duration and scope of processing | E55: Yes | G55: ='P3 Data Subject Rights'!H14 -> 0 | H55: ='P3 Data Subject Rights'!I14 -> 0 | I55: ='P3 Data Subject Rights'!J14 -> 0 | J55: ='P3 Data Subject Rights'!K14 -> 0 | K55: ='P3 Data Subject Rights'!L14 -> 0 | L55: ='P3 Data Subject Rights'!M14 -> 0 | M55: ='P3 Data Subject Rights'!N14 -> 0
B56: c. Identity of the PIC | E56: Yes | G56: ='P3 Data Subject Rights'!H15 -> 0 | H56: ='P3 Data Subject Rights'!I15 -> 0 | I56: ='P3 Data Subject Rights'!J15 -> 0 | J56: ='P3 Data Subject Rights'!K15 -> 0 | K56: ='P3 Data Subject Rights'!L15 -> 0 | L56: ='P3 Data Subject Rights'!M15 -> 0 | M56: ='P3 Data Subject Rights'!N15 -> 0
B57: d. Data subject rights and the process for exercising them | E57: Yes | G57: ='P3 Data Subject Rights'!H16 -> 0 | H57: ='P3 Data Subject Rights'!I16 -> 0 | I57: ='P3 Data Subject Rights'!J16 -> 0 | J57: ='P3 Data Subject Rights'!K16 -> 0 | K57: ='P3 Data Subject Rights'!L16 -> 0 | L57: ='P3 Data Subject Rights'!M16 -> 0 | M57: ='P3 Data Subject Rights'!N16 -> 0
A58: 3 | B58: (For consent) Does the data subject give specific consent for each declared purpose of data processing? If processing serves multiple unrelated purposes, do you provide a list and allow them to choose which ones to consent to? | E58: ='P3 Data Subject Rights'!F17 -> 0 | G58: ='P3 Data Subject Rights'!H17 -> 0 | H58: ='P3 Data Subject Rights'!I17 | I58: ='P3 Data Subject Rights'!J17 | J58: ='P3 Data Subject Rights'!K17 | K58: ='P3 Data Subject Rights'!L17 | L58: ='P3 Data Subject Rights'!M17 | M58: ='P3 Data Subject Rights'!N17 | N58: Reduce | O58: Ensure that consent is specific and purpose-bound, not bundled. When processing personal data for multiple, unrelated purposes, present each purpose separately and allow the data subject to select which purposes they consent to. Avoid requiring all-inclusive consent. Integrate granular consent options in consent forms and systems, and include this requirement in consent management policies and development checklists. | P58: Planned | Q58: Low | R58: SEC. 8, NPC Circular 2023-04 | T58: 7 | U58: Annual or upon any significant change to data processing activities | V58: System/Process Owner
A59: 4 | B59: Do you inform the data subject of their right to object or withdraw consent to the processing of their personal data? | E59: ='P3 Data Subject Rights'!F18 -> 0 | G59: ='P3 Data Subject Rights'!H18 -> 0 | H59: ='P3 Data Subject Rights'!I18 | I59: ='P3 Data Subject Rights'!J18 | J59: ='P3 Data Subject Rights'!K18 | K59: ='P3 Data Subject Rights'!L18 | L59: ='P3 Data Subject Rights'!M18 | M59: ='P3 Data Subject Rights'!N18 | N59: Reduce | O59: Clearly inform data subjects of their right to object to the processing of their personal data, including processing for direct marketing, automated processing, or profiling. Provide mechanisms to object or withdraw consent at any time. Notify data subjects of any changes or amendments to the processing terms and offer an opportunity to withhold or withdraw consent. Integrate these controls in privacy notices, consent forms, and system interfaces. | P59: Planned | Q59: Low | R59: SEC. 34(b), IRR | T59: 7 | U59: Annual or upon any significant change to data processing activities | V59: System/Process Owner
A60: 5 | B60: Do you inform the data subject of the scope and consequences of withdrawing consent or objecting at the start of processing and upon withdrawal/objection? | E60: ='P3 Data Subject Rights'!F19 -> 0 | G60: ='P3 Data Subject Rights'!H19 -> 0 | H60: ='P3 Data Subject Rights'!I19 | I60: ='P3 Data Subject Rights'!J19 | J60: ='P3 Data Subject Rights'!K19 | K60: ='P3 Data Subject Rights'!L19 | L60: ='P3 Data Subject Rights'!M19 | M60: ='P3 Data Subject Rights'!N19 | N60: Reduce | O60: Inform data subjects of their right to object or withdraw consent at the start of processing and again at the point of withdrawal. Clearly explain the scope and consequences, including any further processing, its purposes, and lawful bases relied on. Define a reasonable retention period for personal data after withdrawal, based on lawful bases, industry standards, and operational needs. Reflect these requirements in privacy notices, consent workflows, and internal retention policies. | P60: Planned | Q60: Low | R60: SEC. 13(C)(E), NPC Circular 2023-04 | T60: 7 | U60: Annual or upon any significant change to data processing activities | V60: System/Process Owner
A61: 6 | B61: When a data subject objects, do you stop processing their personal data and comply with the objection unless processing is allowed in Section 12 and 13 of the DPA, excluding consent and legitimate interest? | E61: ='P3 Data Subject Rights'!F20 -> 0 | G61: ='P3 Data Subject Rights'!H20 -> 0 | H61: ='P3 Data Subject Rights'!I20 | I61: ='P3 Data Subject Rights'!J20 | J61: ='P3 Data Subject Rights'!K20 | K61: ='P3 Data Subject Rights'!L20 | L61: ='P3 Data Subject Rights'!M20 | M61: ='P3 Data Subject Rights'!N20 | N61: Reduce | O61: Upon receiving a valid objection or withdrawal of consent, and where no other lawful basis applies, the PIC must stop processing without undue delay, terminate any related activities or services, and delete the personal data. Inform data subjects that withdrawal does not affect prior lawful processing. Ensure systems support real-time consent revocation and flagging of affected records for secure deletion. Update internal SOPs and train staff accordingly. | P61: Planned | Q61: Low | R61: SEC. 13, NPC Circular 2023-04 | T61: 1 | U61: Annual or upon any significant change to data processing activities | V61: System/Process Owner
A62: 7 | B62: Do data subjects have the right to object to the processing of their personal data for direct marketing, profiling, or automated processing when it is the sole basis for decisions that significantly affect them? | E62: ='P3 Data Subject Rights'!F21 -> 0 | G62: ='P3 Data Subject Rights'!H21 -> 0 | H62: ='P3 Data Subject Rights'!I21 | I62: ='P3 Data Subject Rights'!J21 | J62: ='P3 Data Subject Rights'!K21 | K62: ='P3 Data Subject Rights'!L21 | L62: ='P3 Data Subject Rights'!M21 | M62: ='P3 Data Subject Rights'!N21 | N62: Reduce | O62: Ensure data subjects are informed of their right to object to the processing of their personal data, including for direct marketing, profiling, or automated processing. Implement opt-out mechanisms and allow objections at any time. When automated processing is the sole basis for a decision with legal or significant effects, obtain explicit consent. Integrate controls into privacy notices, systems, and staff training. | P62: Planned | Q62: Low | R62: SEC. 34(b), IRR SEC. 18(C), NPC Circular 2023-04 | T62: 7 | U62: Annual or upon any significant change to data processing activities | V62: System/Process Owner
A63: Right to access
A64: 1 | B64: Does the data subject have the right to confirm if their personal data is being processed and access details about its processing? Check all applicable | E64: ='P3 Data Subject Rights'!F23 -> 0 | G64: ='P3 Data Subject Rights'!H23 -> 0 | H64: ='P3 Data Subject Rights'!I23 | I64: ='P3 Data Subject Rights'!J23 | J64: ='P3 Data Subject Rights'!K23 | K64: ='P3 Data Subject Rights'!L23 | L64: ='P3 Data Subject Rights'!M23 | M64: ='P3 Data Subject Rights'!N23 | N64: Reduce | O64: Establish procedures to ensure that data subjects can exercise their right to access and obtain confirmation of processing, including details listed under Section 34(c) of the IRR upon demand. Make access request channels easily accessible, document request handling in standard operating procedures, and train personnel on turnaround times and verification steps. Include access rights in privacy notices, and maintain logs for tracking and audit. | P64: Planned | Q64: Low | R64: SEC. 34(c), IRR | T64: 7 | U64: Annual or upon any significant change to data processing activities | V64: System/Process Owner
B65: a. Content and categories of his or her personal data | E65: ='P3 Data Subject Rights'!F24 -> 0 | G65: ='P3 Data Subject Rights'!H24 -> 0
B66: b. Sources from which personal data was obtained, if not collected from the data subject | E66: ='P3 Data Subject Rights'!F25 -> 0 | G66: ='P3 Data Subject Rights'!H25 -> 0
B67: c. Purposes of processing | E67: ='P3 Data Subject Rights'!F26 -> 0 | G67: ='P3 Data Subject Rights'!H26 -> 0
B68: d. Manner by which personal data were processed | E68: ='P3 Data Subject Rights'!F27 -> 0 | G68: ='P3 Data Subject Rights'!H27 -> 0
B69: e. Automated processes using personal data as the sole basis for decisions that significantly impact the data subject (if applicable) | E69: ='P3 Data Subject Rights'!F28 -> 0 | G69: ='P3 Data Subject Rights'!H28 -> 0
B70: f. Names and addresses of recipients of the personal data (if applicable) | E70: ='P3 Data Subject Rights'!F29 -> 0 | G70: ='P3 Data Subject Rights'!H29 -> 0
B71: g. Date when his or her personal data were last accessed and modified | E71: ='P3 Data Subject Rights'!F30 -> FALSE | G71: ='P3 Data Subject Rights'!H30 -> 0
B72: h. Retention period | E72: ='P3 Data Subject Rights'!F31 -> 0 | G72: ='P3 Data Subject Rights'!H31 -> 0
B73: i. Designation, name or identity, and address of the DPO | E73: ='P3 Data Subject Rights'!F32 -> 0 | G73: ='P3 Data Subject Rights'!H32 -> 0
A74: Right to rectify (Excludes cases requiring a court order, government agency directive, or official legal process) | E74: ='P3 Data Subject Rights'!F33 -> 0
A75: 1 | B75: Does the data subject have the right to dispute inaccuracies in their personal data and have the PIC correct them within the reasonable time? | E75: ='P3 Data Subject Rights'!F34 -> 0 | G75: ='P3 Data Subject Rights'!H34 -> 0 | H75: ='P3 Data Subject Rights'!I34 | I75: ='P3 Data Subject Rights'!J34 | J75: ='P3 Data Subject Rights'!K34 | K75: ='P3 Data Subject Rights'!L34 | L75: ='P3 Data Subject Rights'!M34 | M75: ='P3 Data Subject Rights'!N34 | N75: Reduce | O75: Establish a clear process allowing data subjects to dispute and correct inaccurate or incomplete personal data within a reasonable time. Ensure that requests are addressed immediately and accordingly, unless deemed vexatious or unreasonable. Allow data subjects to provide supplementary statements where needed to complete incomplete data. Reflect this right in the privacy notice, enable requests through accessible channels, and maintain logs for tracking and audit. | P75: Planned | Q75: Low | R75: SEC. 34(d), IRR | T75: 7 | U75: Annual or upon any significant change to data processing activities | V75: System/Process Owner
A76: 2 | B76: If personal data has been corrected,
B77: a. Does the PIC ensure that both the new and retracted information are accessible and received simultaneously by the intended recipients? | E77: ='P3 Data Subject Rights'!F36 -> 0 | G77: ='P3 Data Subject Rights'!H36 -> 0 | H77: ='P3 Data Subject Rights'!I36 | I77: ='P3 Data Subject Rights'!J36 | J77: ='P3 Data Subject Rights'!K36 | K77: ='P3 Data Subject Rights'!L36 | L77: ='P3 Data Subject Rights'!M36 | M77: ='P3 Data Subject Rights'!N36 | N77: Reduce | O77: When personal data is corrected or retracted, ensure that both the updated and withdrawn information are made accessible and are simultaneously transmitted to all intended recipients. Implement procedures and system controls to track disclosures, update third parties, and confirm receipt of corrected data. Document these obligations in data sharing agreements and internal SOPs. | P77: Planned | Q77: Low | R77: SEC. 34(d), IRR | T77: 30 | U77: Annual or upon any significant change to data processing activities | V77: System/Process Owner
B78: b. Does the PIC inform recipients or third parties who previously received the inaccurate personal data about its inaccuracy and subsequent correction? | E78: ='P3 Data Subject Rights'!F37 -> 0 | G78: ='P3 Data Subject Rights'!H37 -> 0 | H78: ='P3 Data Subject Rights'!I37 | K78: ='P3 Data Subject Rights'!L37 | L78: ='P3 Data Subject Rights'!M37 | M78: ='P3 Data Subject Rights'!N37 | N78: Reduce | O78: Upon reasonable request of the data subject, inform all recipients or third parties who previously received the inaccurate personal data of its inaccuracy and subsequent rectification. Establish procedures for tracking data disclosures and facilitating timely notifications. Reflect this obligation in data sharing agreements and internal correction protocols. | P78: Planned | Q78: Low | R78: SEC. 34(d), IRR | T78: 30 | U78: Annual or upon any significant change to data processing activities | V78: System/Process Owner
A79: Right to erasure or blocking
A80: 1 | B80: Does the data subject have the right to request the suspension, withdrawal, blocking, removal, or destruction of their personal data from the PIC’s live and backup systems upon discovery and substantial proof of the following? Note: Personal data is: a. Incomplete, outdated, false, or unlawfully obtained b. Used for unauthorized purpose c. No longer necessary for the purpose for which they were collected d. Prejudicial to the data subject, unless justified by freedom of speech, of expression, or of the press, or otherwise authorized | E80: ='P3 Data Subject Rights'!F39 -> 0 | G80: ='P3 Data Subject Rights'!H39 -> 0 | H80: ='P3 Data Subject Rights'!I39 | I80: ='P3 Data Subject Rights'!J39 | J80: ='P3 Data Subject Rights'!K39 | K80: ='P3 Data Subject Rights'!L39 | L80: ='P3 Data Subject Rights'!M39 | M80: ='P3 Data Subject Rights'!N39 | N80: Reduce | O80: Enable data subjects to request suspension, blocking, withdrawal, removal, or destruction of their personal data from both live and backup systems. Inform data subjects of the consequences of erasure, and notify third parties or recipients of such deletion. For publicly available data, take reasonable and appropriate steps (e.g., request delisting or removal) from third-party platforms. Document and integrate these measures in the data retention, disposal, and data subject rights procedures. | P80: Planned | Q80: Low | R80: SEC. 34(e), IRR | T80: 7 | U80: Annual or upon any significant change to data processing activities | V80: System/Process Owner
A81: Right to data portability (Applicable if processing is based on consent or contract AND processed electronically)
A82: 1 | B82: Does the data subject have the right to obtain a copy of their personal data from the PIC and have it transmitted to another PIC in a commonly used, structured, and electronic format? | E82: ='P3 Data Subject Rights'!F41 -> 0 | G82: ='P3 Data Subject Rights'!H41 -> 0 | H82: ='P3 Data Subject Rights'!I41 | I82: ='P3 Data Subject Rights'!J41 | J82: ='P3 Data Subject Rights'!K41 | K82: ='P3 Data Subject Rights'!L41 | L82: ='P3 Data Subject Rights'!M41 | M82: ='P3 Data Subject Rights'!N41 | N82: Reduce | O82: Establish a process to allow data subjects to request and obtain a copy of their personal data in a commonly used, machine-readable, structured format (e.g., XML, JSON, CSV), and to transmit such data to another PIC. Limit portability to personal data provided by the data subject. Ensure that this right does not adversely affect the rights of others and apply security measures to prevent unintentional disclosure of third-party data. Receiving PICs must be prohibited from using any included third-party data for their own purposes. | P82: Planned | Q82: Low | R82: SEC. 36, IRR | T82: 7 | U82: Annual or upon any significant change to data processing activities | V82: System/Process Owner
A83: Right to file a complaint / damages
A84: 1 | B84: Do you inform the data subject that they have the right to file a complaint with the NPC or be indemnified for damages caused by inaccurate, incomplete, outdated, false, unlawfully obtained, or unauthorized use of their personal data? | E84: ='P3 Data Subject Rights'!F43 -> 0 | G84: ='P3 Data Subject Rights'!H43 -> 0 | H84: ='P3 Data Subject Rights'!I43 | I84: ='P3 Data Subject Rights'!J43 | J84: ='P3 Data Subject Rights'!K43 | K84: ='P3 Data Subject Rights'!L43 | L84: ='P3 Data Subject Rights'!M43 | M84: ='P3 Data Subject Rights'!N43 | N84: Reduce | O84: Clearly inform data subjects—through privacy notices of their right to seek indemnification for any damage caused by inaccurate, false, outdated, unlawfully obtained, or unauthorized use of personal data. State that data subjects may file a complaint with the NPC under its Rules of Procedure. Update internal SOPs to handle such requests and train relevant teams to ensure consistent, rights-based responses. | P84: Planned | Q84: Low | R84: SEC. 34(f), IRR | T84: 7 | U84: Annual or upon any significant change to data processing activities | V84: System/Process Owner
A85: Organizational Security
A86: No. | B86: Questions | E86: Yes/No/N/A | G86: Response | H86: Threats/Vulnerabilities | I86: Risk | J86: Legal Basis | K86: Impact | L86: Probability | M86: Risk Rating | N86: Risk Treatment | O86: Mitigation Measure | P86: Status | Q86: Residual Risk Rating | R86: Control Reference | S86: Start Date | T86: Completion Date | U86: Review Frequency | V86: Risk Owner
A87: 1 | B87: Have you appointed and registered a data protection officer with the National Privacy Commission (NPC)? | E87: No | G87: ='P3 Data Security'!H4 -> 0 | H87: ='P3 Data Security'!I4 | I87: ='P3 Data Security'!J4 | J87: ='P3 Data Security'!K4 | K87: ='P3 Data Security'!L4 | L87: ='P3 Data Security'!M4 | M87: ='P3 Data Security'!N4 | N87: Reduce | O87: Designate and register a qualified Data Protection Officer (DPO) with the National Privacy Commission (NPC), in compliance with the Data Privacy Act (DPA), its IRR, and relevant NPC issuances. The DPO shall be responsible for ensuring privacy compliance, managing data protection strategies, and acting as the main contact for the NPC and data subjects. Responsibilities must be documented and supported by adequate resources. | P87: Planned | Q87: Low | R87: SEC. 26(a), IRR SEC. 4(A), NPC Circular 2023-06 NPC Circular 2022-04 | T87: 7 | U87: Annual or upon any significant change to data processing activities | V87: System/Process Owner
A88: 2 | B88: Have you registered this project or system with the NPC? | E88: ='P3 Data Security'!F5 -> 0 | G88: ='P3 Data Security'!H5 -> 0 | H88: ='P3 Data Security'!I5 | I88: ='P3 Data Security'!J5 | J88: ='P3 Data Security'!K5 | K88: ='P3 Data Security'!L5 | L88: ='P3 Data Security'!M5 | M88: ='P3 Data Security'!N5 | N88: Reduce | O88: Register the organization’s data processing systems with the National Privacy Commission (NPC) in accordance with the Data Privacy Act (DPA), its IRR, and all relevant NPC circulars and advisories. Maintain a record of all processing systems and ensure timely updates or renewals of registration as required. Integrate this step in project onboarding and compliance checklists. | P88: Planned | Q88: Low | R88: SEC. 4(B), NPC Circular 2023-06 NPC Circular 2022-04 | T88: 7 | U88: Annual or upon any significant change to data processing activities | V88: System/Process Owner
A89: 3 | B89: Do you have an inventory of this project or system? Check all present | E89: ='P3 Data Security'!F6 -> 0 | G89: ='P3 Data Security'!H6 -> 0 | H89: ='P3 Data Security'!I6 | I89: ='P3 Data Security'!J6 | J89: ='P3 Data Security'!K6 | K89: ='P3 Data Security'!L6 | L89: ='P3 Data Security'!M6 | M89: ='P3 Data Security'!N6 | N89: Reduce | O89: Create and maintain an inventory of all data processing systems and activities, as required under Section 26(c) and (e) of the IRR. The inventory must clearly describe each processing system and the roles and responsibilities of individuals with access to personal data. Integrate the inventory into privacy governance tools and regularly review and update it to reflect changes. | P89: Planned | Q89: Low | R89: SEC. 26(c)(e), IRR SEC. 4(C), NPC Circular 2023-04 | T89: 7 | U89: Annual or upon any significant change to data processing activities | V89: System/Process Owner
B90: a. Purpose of processing of personal data, including future processing or data sharing. | E90: ='P3 Data Security'!F7 -> FALSE | G90: ='P3 Data Security'!H7 -> 0
B91: b. Categories of data subjects, personal data, and recipients involved. | E91: ='P3 Data Security'!F8 -> FALSE | G91: ='P3 Data Security'!H8 -> 0
B92: c. Data flow from collection to disposal, including retention periods. | E92: ='P3 Data Security'!F9 -> FALSE | G92: ='P3 Data Security'!H9 -> 0
B93: d. Security measures (organizational, physical, and technical) | E93: ='P3 Data Security'!F10 -> FALSE | G93: ='P3 Data Security'!H10 -> 0
B94: e. Contacts details of the PIC, joint controller (if applicable), representative, and compliance officer or DPO. | E94: ='P3 Data Security'!F11 -> FALSE | G94: ='P3 Data Security'!H11 -> 0
A95: 4 | B95: Do you conduct a PIA for this project or system annually and update it when necessary (e.g., new features, major changes, new regulations, new contracts entered), considering the minimum requirements? Check all present | E95: ='P3 Data Security'!F12 -> 0 | H95: ='P3 Data Security'!I12 | I95: ='P3 Data Security'!J12 | J95: ='P3 Data Security'!K12 | K95: ='P3 Data Security'!L12 | L95: ='P3 Data Security'!M12 | M95: ='P3 Data Security'!N12 | N95: Reduce | O95: Conduct a Privacy Impact Assessment (PIA) on data processing systems and off-the-shelf software and update it as necessary, such as when there are new features, major changes, new regulations, or third-party contracts. Monitor and update previously assessed and newly identified controls. Incorporate PIA results into the organization's Privacy Management Program to ensure continuous risk-based improvements. | P95: Planned | Q95: Low | R95: SEC. 4(D), 5, 6, 7, NPC Circular 2023-06 | T95: 30 | U95: Annual or upon any significant change to data processing activities | V95: System/Process Owner
B96: a. Data inventory
B97: i. Types and volume of personal data held, including employee records | E97: ='P3 Data Security'!F14 -> FALSE | G97: ='P3 Data Security'!H14 -> 0
B98: ii. List and location of repositories of personal data | E98: ='P3 Data Security'!F15 -> FALSE | G98: ='P3 Data Security'!H15 -> 0
B99: iii. Storage media used | E99: ='P3 Data Security'!F16 -> FALSE | G99: ='P3 Data Security'!H16 -> 0
B100: iv. Risks associated with data processing | E100: ='P3 Data Security'!F17 -> FALSE | G100: ='P3 Data Security'!H17 -> 0
B101: v. Processing operations across the data lifecycle, from collection to disposal | E101: ='P3 Data Security'!F18 -> FALSE | G101: ='P3 Data Security'!H18 -> 0
B102: b. Systematic Description | E102: ='P3 Data Security'!F19 -> FALSE | G102: ='P3 Data Security'!H19 -> 0
B103: c. Assessment of:
...

Sheet Privacy Risk Map
D2: Privacy Risk Map
B3: Impact | C3: 4 | D3: 4 | E3: 8 | F3: 12 | G3: 16
C4: 3 | D4: 3 | E4: 6 | F4: 9 | G4: 12
C5: 2 | D5: 2 | E5: 4 | F5: 6 | G5: 8
C6: 1 | D6: 1 | E6: 2 | F6: 3 | G6: 4
D7: 1 | E7: 2 | F7: 3 | G7: 4
D8: Probability
B10: Impact
B11: Rating | D11: Type | F11: Description
B12: 1 | D12: Negligible | F12: The data subjects will either not be affected or may experience minor inconveniences that they can easily manage.
B13: 2 | D13: Limited | F13: The data subject may face major inconveniences but can still manage to overcome them with some difficulty.
B14: 3 | D14: Significant | F14: The data subjects may face major inconveniences that they might overcome, but it will be very difficult.
B15: 4 | D15: Maximum | F15: The data subjects may face serious or even irreversible consequences that they might not be able to overcome.
B17: Probability
B18: Rating | D18: Type | F18: Description
B19: 1 | D19: Unlikely | F19: Rare chance; not expected but possible.
B20: 2 | D20: Possible | F20: Could happen sometimes.
B21: 3 | D21: Likely | F21: Happens regularly or often.
B22: 4 | D22: Almost Certain | F22: Expected to happen in most cases.

Sheet Sign-Off
C5: PIA Sign-off
D7: Designation | E7: Name | F7: Date | G7: Signature
C8: Prepared By: | D8: <System/Process Owner>
C9: Reviewed By: | D9: <Data Protection Officer/ Compliance Officer for Privacy>
C10: Approved By: | D10: <Group Head>
